Workbook
Name Comprar: [1]Param!#REF!
Name Comprar: [1]Param!#REF!
Name Comprar: [1]Param!#REF!
Name Comprar: [1]Param!#REF!
Name Comprar: [1]Param!#REF!
Name Comprar: [1]Param!#REF!
Name início_da_tarefa: [2]CronogramaDeProjeto!$E1
Name Início_do_projeto: '[3]Gráfico de Gantt'!$G$5
Name Início_do_projeto: '[3]Gráfico de Gantt'!$G$5
Name Início_do_projeto: '[4]Gráfico de Gantt'!$G$5
Name Início_do_projeto: '[4]Gráfico de Gantt'!$G$5
Name Início_do_projeto: '[3]Gráfico de Gantt'!$G$5
Name Início_do_projeto: '[4]Gráfico de Gantt'!$G$5
Name Início_do_projeto: '[3]Gráfico de Gantt'!$G$5
Name Início_do_projeto: '[4]Gráfico de Gantt'!$G$5
Name Início_do_projeto: '[5]Gráfico de Gantt'!$G$5
Name Início_do_projeto: '[3]Gráfico de Gantt'!$G$5
Name Início_do_projeto: '[6]Gráfico de Gantt'!$G$5
Name Início_do_projeto: 'Gráfico de Gantt'!$G$5
Name Periodicidade: [7]Param!$AB$5:$AB$9
Name progresso_da_tarefa: [2]CronogramaDeProjeto!$D1
Name Semana_de_exibição: '[3]Gráfico de Gantt'!$G$6
Name Semana_de_exibição: '[3]Gráfico de Gantt'!$G$6
Name Semana_de_exibição: '[4]Gráfico de Gantt'!$G$6
Name Semana_de_exibição: '[4]Gráfico de Gantt'!$G$6
Name Semana_de_exibição: '[3]Gráfico de Gantt'!$G$6
Name Semana_de_exibição: '[4]Gráfico de Gantt'!$G$6
Name Semana_de_exibição: '[3]Gráfico de Gantt'!$G$6
Name Semana_de_exibição: '[4]Gráfico de Gantt'!$G$6
Name Semana_de_exibição: '[5]Gráfico de Gantt'!$G$6
Name Semana_de_exibição: '[3]Gráfico de Gantt'!$G$6
Name Semana_de_exibição: '[6]Gráfico de Gantt'!$G$6
Name Semana_de_exibição: 'Gráfico de Gantt'!$G$6
Name Status: [1]Param!#REF!
Name término_da_tarefa: [2]CronogramaDeProjeto!$F1
Name VersaoExcel: [7]Param!$D$15:$E$15
Name VersaoSR: [7]Param!$C$24:$C$26

Sheet Project Charter

Sheet WBS-MACRO-ATIVIDADE

Sheet WBS_Detalhado (ordem etapas)
B7: 4.1 Plano de ação detalhado da WBS (com dependência, tempo e recurso)
B9: Ref | C9: Etapas – Atividades - | D9: Dependência | E9: Data Início | F9: Data Fim | G9: Duração em dias | H9: Conclusão | I9: Responsável | J9: Recursos | K9: Custos | L9: Obs
B10: 1 | C10: Iniciação | D10: 1 | E10: 45880 | F10: 45887 | G10: 8 | H10: 1ª | I10: GERENTE DE PROJETO | J10: PESSOAS
B11: 1A | C11: DEFINIÇÃO DE OBJETIVOS DO PROJETO | D11: 1 | E11: 45880 | F11: 45884 | G11: 5 | H11: 1ª | I11: GERENTE DE PROJETO | J11: PESSOAS | K11: 5000
B12: 1B | C12: FORMAÇÃO DA EQUIPE DE DESIGN E DESENVOLVIMENTO | D12: 1A | E12: 45884 | F12: 45885 | G12: 1 | H12: 1ª | I12: GERENTE DE PROJETO | J12: PESSOAS | K12: 1000
B13: 1C | C13: IDENTIFICAÇÃO DE FUNCIONALIDADES E RECURSOS | D13: 1A | E13: 45884 | F13: 45887 | G13: 3 | H13: 1ª | I13: GERENTE DE PROJETO | J13: PESSOAS | K13: 3000
B14: 1D | C14: IDENTIFICAÇÃO DE STAKEHOLDERS | D14: 1A | E14: 45884 | F14: 45885 | G14: 1 | H14: 1ª | I14: GERENTE DE PROJETO | J14: PESSOAS | K14: 1000
B15: 2 | C15: Planejamento | D15: 1C | E15: 45887 | F15: 45893 | G15: 10 | H15: 2ª | I15: GERENTE DE PROJETO | J15: PESSOAS | K15: =SUM(K11:K14) -> 10000
B16: 2A | C16: ANÁLISE DE MERCADO | D16: 2 | E16: 45887 | F16: 45888 | G16: 1 | H16: 2ª | I16: GERENTE DE PROJETO | J16: PESSOAS | K16: 2000
B17: 2B | C17: LEVANTAMENTO DE REQUISITOS | D17: 2A | E17: 45889 | F17: 45891 | G17: 2 | H17: 2ª | I17: GERENTE DE PROJETO | J17: PESSOAS | K17: 2000
B18: 2C | C18: DOCUMENTAÇÃO DE REQUISITOS FUNCIONAIS | D18: 2A | E18: 45889 | F18: 45891 | G18: 2 | H18: 2ª | I18: GERENTE DE PROJETO | J18: PESSOAS | K18: 1000
B19: 2D | C19: DOCUMENTAÇÃO DE REQUISITOS NÃO FUNCIONAIS | D19: 2A | E19: 45889 | F19: 45891 | G19: 2 | H19: 2ª | I19: GERENTE DE PROJETO | J19: PESSOAS | K19: 1000
B20: 2E | C20: IDENTIFICAÇÃO DO CAMINHO CRÍTICO | D20: 2B,2C,2D | E20: 45892 | F20: 45893 | G20: 1 | H20: 2ª | I20: GERENTE DE PROJETO | J20: PESSOAS | K20: 1000
B21: 2F | C21: PLANEJAMENTO DE SEGURANÇA E LGPD | D21: 2B,2C,2D | E21: 45892 | F21: 45893 | G21: 1 | H21: 2ª | I21: GERENTE DE PROJETO | J21: PESSOAS | K21: 2000
B22: 2G | C22: DEFINIÇÃO DE PROTOCOLOS DE PRIVACIDADE (DADOS) | D22: 2B,2C,2D | E22: 45892 | F22: 45893 | G22: 1 | H22: 2ª | I22: GERENTE DE PROJETO | J22: PESSOAS | K22: 3000
B23: 3 | C23: Design e Prototipagem | D23: 2B,2E,2F,2G | E23: 45894 | F23: 45902 | G23: 19 | H23: 3ª | I23: DESIGN | J23: PESSOAS + SOFTWARE | K23: =SUM(K16:K22) -> 12000
B24: 3A | C24: REALIZAR O DESIGN DA INTERFACE DO USUÁRIO(UI) | D24: 3 | E24: 45894 | F24: 45897 | G24: =F24-E24 -> 3 | H24: 3ª | I24: DESIGN | J24: PESSOAS + SOFTWARE | K24: 2000
B25: 3B | C25: DEFINIR PALETA DE CORES E TIPOGRAFIA | D25: 3A | E25: 45894 | F25: 45894 | G25: 1 | H25: 3ª | I25: DESIGN | J25: PESSOAS + SOFTWARE | K25: 1000
B26: 3C | C26: CRIAR ÍCONES E ELEMENTOS VISUAIS | D26: 3A | E26: 45894 | F26: 45894 | G26: 1 | H26: 3ª | I26: DESIGN | J26: PESSOAS + SOFTWARE | K26: 1000
B27: 3D | C27: GARANTIR CONSISTÊNCIA VISUAL | D27: 3A | E27: 45894 | F27: 45897 | G27: =F27-E27 -> 3 | H27: 3ª | I27: DESIGN | J27: PESSOAS + SOFTWARE | K27: 1000
B28: 3E | C28: CRIAÇÃO DE PROTÓTIPO INTERATIVO | D28: 3D | E28: 45894 | F28: 45898 | G28: =F28-E28 -> 4 | H28: 3ª | I28: DESIGN | J28: PESSOAS + SOFTWARE | K28: 1000
B29: 3F | C29: EXPERIÊNCIA DO USUÁRIO (UX) | D29: 3D | E29: 45894 | F29: 45898 | G29: =F29-E29 -> 4 | H29: 3ª | I29: DESIGN | J29: PESSOAS + SOFTWARE | K29: 2000
B30: 3G | C30: DEFINIÇÃO DE PERSONAS | D30: 3F | E30: 45898 | F30: 45899 | G30: =F30-E30 -> 1 | H30: 3ª | I30: DESIGN | J30: PESSOAS + SOFTWARE | K30: 4000
B31: 3H | C31: GARANTIR ACESSIBILIDADE E USABILIDADE | D31: 3F | E31: 45901 | F31: 45902 | G31: =F31-E31 -> 1 | H31: 3ª | I31: DESIGN | J31: PESSOAS + SOFTWARE | K31: 1000
B32: 3I | C32: MAPEAR JORNADA DO USUÁRIO | D32: 3E | E32: 45901 | F32: 45902 | G32: =F32-E32 -> 1 | H32: 3ª | I32: DESIGN | J32: PESSOAS + SOFTWARE | K32: 2000
B33: 3J | C33: VALIDAÇÃO INICIAL COM STAKEHOLDERS | D33: 3H,3F,3E | E33: 45901 | F33: 45902 | G33: 1 | H33: 3ª | I33: DESIGN | J33: PESSOAS + SOFTWARE | K33: 1000
B34: 4 | C34: Desenvolvimento | D34: 3J | E34: 45903 | F34: 45940 | G34: 42 | H34: 4ª | I34: DESENVOLVIMENTO | J34: PESSOAS + SOFTWARE + HADWARE | K34: =SUM(K24:K33) -> 16000
B35: 4A | C35: DEFINIR A ESTRUTURA DO SITE | D35: 4 | E35: 45903 | F35: 45904 | G35: =F35-E35 -> 1 | H35: 4ª | I35: DESENVOLVIMENTO | J35: PESSOAS + SOFTWARE + HADWARE | K35: 2000
B36: 4B | C36: PREPARAÇÃO DO AMBIENTE | D36: 4A | E36: 45903 | F36: 45904 | G36: =F36-E36 -> 1 | H36: 4ª | I36: DESENVOLVIMENTO | J36: PESSOAS + SOFTWARE + HADWARE | K36: 1000
B37: 4C | C37: CONFIGURAÇÃO DE REPOSITÓRIO GITHUB | D37: 4A | E37: 45903 | F37: 45904 | G37: =F37-E37 -> 1 | H37: 4ª | I37: DESENVOLVIMENTO | J37: PESSOAS + SOFTWARE + HADWARE | K37: 1000
B38: 4D | C38: DEFINIÇÃO DO AMBIENTE DE HOSPEDAGEM | D38: 4A | E38: 45903 | F38: 45904 | G38: =F38-E38 -> 1 | H38: 4ª | I38: DESENVOLVIMENTO | J38: PESSOAS + SOFTWARE + HADWARE | K38: 10000
B39: 4E | C39: INSTALAÇÃO DO ETL E BI | D39: 4A | E39: 45903 | F39: 45904 | G39: =F39-E39 -> 1 | H39: 4ª | I39: DESENVOLVIMENTO | J39: PESSOAS + SOFTWARE + HADWARE | K39: 1000
B40: 4F | C40: CÓDIGO FRONT-END | D40: 4A | E40: 45905 | F40: 45919 | G40: =F40-E40 -> 14 | H40: 4ª | I40: DESENVOLVIMENTO | J40: PESSOAS + SOFTWARE + HADWARE | K40: 2000
B41: 4G | C41: ESTRUTURAÇÃO INICIAL DE INTERFACE | D41: 4F | E41: 45905 | F41: 45919 | G41: =F41-E41 -> 14 | H41: 4ª | I41: DESENVOLVIMENTO | J41: PESSOAS + SOFTWARE + HADWARE | K41: 1000
B42: 4H | C42: IMPLEMENTAÇÃO DE KPIs PRINCIPAIS | D42: 4G | E42: 45905 | F42: 45919 | G42: =F42-E42 -> 14 | H42: 4ª | I42: DESENVOLVIMENTO | J42: PESSOAS + SOFTWARE + HADWARE | K42: 1000
B43: 4I | C43: CRIAÇÃO DE GRÁFICOS INTERATIVOS | D43: 4G | E43: 45905 | F43: 45919 | G43: =F43-E43 -> 14 | H43: 4ª | I43: DESENVOLVIMENTO | J43: PESSOAS + SOFTWARE + HADWARE | K43: 3000
B44: 4J | C44: DESENVOLVIMENTO DE FILTROS DINÂMICOS | D44: 4I | E44: 45905 | F44: 45919 | G44: =F44-E44 -> 14 | H44: 4ª | I44: DESENVOLVIMENTO | J44: PESSOAS + SOFTWARE + HADWARE | K44: 2000
B45: 4K | C45: EXPORTAÇÃO DE RELATÓRIOS | D45: 4J | E45: 45905 | F45: 45919 | G45: =F45-E45 -> 14 | H45: 4ª | I45: DESENVOLVIMENTO | J45: PESSOAS + SOFTWARE + HADWARE | K45: 1000
B46: 4L | C46: CÓDIGO BACK-END | D46: 3E,2G | E46: 45898 | F46: 45940 | G46: =F46-E46 -> 42 | H46: 4ª | I46: DESENVOLVIMENTO | J46: PESSOAS + SOFTWARE + HADWARE | K46: 4000
B47: 4M | C47: ESTRUTURAÇÃO DO BANCO DE DADOS | D47: 2G | E47: 45899 | F47: 45940 | G47: =F47-E47 -> 41 | H47: 4ª | I47: DESENVOLVIMENTO | J47: PESSOAS + SOFTWARE + HADWARE | K47: 1000
... B57: 4W | C57: INTEGRAÇÃO AO DASHBOARD (WEB OU APP) | D57: 4Q,4F,4L | E57: 45920 | F57: 45940 | G57: =F57-E57 -> 20 | H57: 4ª | I57: DESENVOLVIMENTO | J57: PESSOAS + SOFTWARE + HADWARE | K57: 1000
B58: 5 | C58: Integração | D58: 4W,4F,4L | E58: 45941 | F58: 45945 | G58: =F59-E59 -> 4 | H58: 5ª | I58: SEGURANÇA | J58: SOFTWARE + SERVIDORES | K58: =SUM(K35:K52) -> 40000
B59: 5A | C59: INTEGRAÇÃO DE FONTES DE DADOS | D59: 5 | E59: 45941 | F59: 45945 | G59: 1 | H59: 5ª | I59: SEGURANÇA | J59: SOFTWARE + SERVIDORES | K59: 2000
B60: 5B | C60: GARANTIR A SEGURANÇA E PRIVACIDADE | D60: 5A | E60: 45941 | F60: 45945 | G60: 1 | H60: 5ª | I60: SEGURANÇA | J60: SOFTWARE + SERVIDORES | K60: 2000
B61: 5C | C61: SINCRONIZAÇÃO DE DADOS NO BANCO PRINCIPAL | D61: 5A,5B | E61: 45941 | F61: 45945 | G61: 1 | H61: 5ª | I61: SEGURANÇA | J61: SOFTWARE + SERVIDORES | K61: 2000
B62: 6 | C62: Testes | D62: 5C | E62: 45946 | F62: 45950 | G62: =F62-E62 -> 4 | H62: 6ª | I62: QUALIDADE | J62: PESSOAS + FERRAMENTAS | K62: =SUM(K59:K61) -> 6000
B63: 6A | C63: TESTES UNITÁRIOS | D63: 5A | E63: 45946 | F63: 45947 | G63: 1 | H63: 6ª | I63: QUALIDADE | J63: PESSOAS + FERRAMENTAS | K63: 1000
B64: 6B | C64: DEFINIÇÃO DE CENÁRIOS DE TESTE | D64: 6A | E64: 45946 | F64: 45947 | G64: 1 | H64: 6ª | I64: QUALIDADE | J64: PESSOAS + FERRAMENTAS | K64: 1000
B65: 6C | C65: REGISTROS DE RESULTADOS EM RELATÓRIOS DE TESTES | D65: 6B | E65: 45946 | F65: 45947 | G65: 1 | H65: 6ª | I65: QUALIDADE | J65: PESSOAS + FERRAMENTAS | K65: 1000
B66: 6D | C66: CORREÇÃO DE BUGS IDENTIFICADOS | D66: 6C | E66: 45946 | F66: 45947 | G66: 1 | H66: 6ª | I66: QUALIDADE | J66: PESSOAS + FERRAMENTAS | K66: 1000
B67: 6E | C67: TESTES DE USABILIDADE | D67: 6D | E67: 45947 | F67: 45948 | G67: 1 | H67: 6ª | I67: QUALIDADE | J67: PESSOAS + FERRAMENTAS | K67: 1000
B68: 6F | C68: APLICAÇÃO DE TESTES PILOTO COM USUÁRIOS | D68: 6E | E68: 45947 | F68: 45948 | G68: 1 | H68: 6ª | I68: QUALIDADE | J68: PESSOAS + FERRAMENTAS | K68: 1000
B69: 6G | C69: COLETA DE FEEDBACK SOBRE NAVEGAÇÃO | D69: 6F | E69: 45948 | F69: 45949 | G69: 1 | H69: 6ª | I69: QUALIDADE | J69: PESSOAS + FERRAMENTAS | K69: 1000
B70: 6H | C70: VALIDAÇÃO DE RESPONSIVIDADE | D70: 6G | E70: 45948 | F70: 45949 | G70: 1 | H70: 6ª | I70: QUALIDADE | J70: PESSOAS + FERRAMENTAS | K70: 1000
B71: 6I | C71: PREPARAÇÃO DE AMBIENTE DE HOMOLOGAÇÃO | D71: 6H | E71: 45949 | F71: 45950 | G71: 1 | H71: 6ª | I71: QUALIDADE | J71: PESSOAS + FERRAMENTAS | K71: 1000
B72: 6J | C72: HOMOLOGAÇÃO | D72: 6I | E72: 45949 | F72: 45950 | G72: 1 | H72: 6ª | I72: QUALIDADE | J72: PESSOAS + FERRAMENTAS | K72: 1000
B73: 6K | C73: DEMONSTRAÇÃO DO DASHBOARD PARA O CLIENTE | D73: 6J | E73: 45949 | F73: 45950 | G73: 1 | H73: 6ª | I73: QUALIDADE | J73: PESSOAS + FERRAMENTAS | K73: 1000
B74: 6L | C74: AJUSTES FINAIS E LIBERAÇÃO PARA PRODUÇÃO | D74: 6K | E74: 45949 | F74: 45950 | G74: 1 | H74: 6ª | I74: QUALIDADE | J74: PESSOAS + FERRAMENTAS | K74: 1000
B75: 7 | C75: Lançamento (Stakeholders internos) | D75: 6L | E75: 45951 | F75: 45952 | G75: 1 | H75: 7ª | I75: GERENTE DE PROJETO | J75: PESSOAS | K75: =SUM(K63:K74) -> 12000
B76: 7A | C76: ATIVAÇÃO DO DASHBOARD EM PRODUÇÃO | D76: 6L | E76: 45951 | F76: 45952 | G76: 1 | H76: 7ª | I76: GERENTE DE PROJETO | J76: PESSOAS | K76: 1000
B77: 7B | C77: MONITORAMENTO NAS PRIMEIRAS HORAS DE USO | D77: 7A | E77: 45951 | F77: 45952 | G77: 1 | H77: 7ª | I77: GERENTE DE PROJETO | J77: PESSOAS | K77: 1000
B78: 7C | C78: SUPORTE INICIAL | D78: 7B | E78: 45951 | F78: 45952 | G78: 1 | H78: 7ª | I78: GERENTE DE PROJETO | J78: PESSOAS | K78: 1000
A79: . | B79: 7D | C79: REUNIÃO DE ALINHAMENTO COM STAKEHOLDERS | D79: 7C | E79: 45951 | F79: 45952 | G79: 1 | H79: 7ª | I79: GERENTE DE PROJETO | J79: PESSOAS | K79: 1000
B80: 8 | C80: Pós-lançamento (Stakeholders internos) | D80: 7D | E80: 45953 | F80: 45955 | G80: =F80-E80 -> 2 | H80: 8ª | I80: EQUIPE TÉCNICA | J80: PESSOAS | K80: =SUM(K76:K79) -> 4000
B81: 8A | C81: MONITORAÇÃO DE MÉTRICAS DE USO DO DASHBOARD | D81: 7D | E81: 45953 | F81: 45955 | G81: 2 | H81: 8ª | I81: EQUIPE TÉCNICA | J81: PESSOAS | K81: 1000
B82: 8B | C82: REALIZAÇÃO DE ATUALIZAÇÕES | D82: 8A | E82: 45953 | F82: 45955 | G82: 2 | H82: 8ª | I82: EQUIPE TÉCNICA | J82: PESSOAS | K82: 1000
B83: 8C | C83: SUPORTE E SOLUÇÃO PARA STAKHOLDERS | D83: 8B | E83: 45953 | F83: 45955 | G83: 2 | H83: 8ª | I83: EQUIPE TÉCNICA | J83: PESSOAS | K83: 1000
B84: 9 | C84: Avaliação e Aperfeiçoamento | D84: 8C | E84: 45956 | F84: 45958 | G84: =F84-E84 -> 2 | H84: 9ª | I84: EQUIPE TÉCNICA | J84: PESSOAS | K84: =SUM(K81,K82,K83) -> 3000
B85: 9A | C85: COLETA DE FEEDBACKS | D85: 8C | E85: 45956 | F85: 45958 | G85: 1 | H85: 9ª | I85: EQUIPE TÉCNICA | J85: PESSOAS | K85: 1000
B86: 9B | C86: IMPLEMENTAÇÃO DE MELHORIAS CONTÍNUAS | D86: 9A | E86: 45956 | F86: 45958 | G86: 1 | H86: 9ª | I86: EQUIPE TÉCNICA | J86: PESSOAS | K86: 1000
B87: 9C | C87: ADAPTAÇÃO AO MERCADO | D87: 9B | E87: 45956 | F87: 45958 | G87: 1 | H87: 9ª | I87: EQUIPE TÉCNICA | J87: PESSOAS | K87: 1000
B88: 10 | C88: Expansão | D88: 9C | E88: 45959 | F88: 45960 | G88: =F88-E88 -> 1 | H88: 10ª | I88: EQUIPE TÉCNICA | J88: PESSOAS | K88: =SUM(K85:K87) -> 3000
B89: 10A | C89: ANÁLISE DE OPORTUNIDADES DE NOVOS SEGMENTOS | D89: 9C | E89: 45959 | F89: 45960 | G89: 1 | H89: 10ª | I89: EQUIPE TÉCNICA | J89: PESSOAS | K89: 1000
B90: 10B | C90: IMPLEMENTAÇÃO DE APP MOBILE | D90: 10A | E90: 45959 | F90: 45960 | G90: 1 | H90: 10ª | I90: EQUIPE TÉCNICA | J90: PESSOAS | K90: 1000
K91: =SUM(K89:K90) -> 2000
D92: TOTAL | K92: =SUM(K15+K23+K34+K58+K75+K80+K62+K84+K88+K91) -> 108000

Sheet WBS_Detalhado (ordem depend)
B6: 4.2 Plano de ação detalhado da WBS (com dependência, tempo e recurso)
B8: Ref | C8: Etapas – Atividades - | D8: Dependência | E8: Duração em semanas | F8: Conclusão | G8: Responsável | H8: Recursos | I8: Obs
B9: 1A | C9: DEFINIÇÃO DOS OBJETIVOS DO PROJETO | E9: 1 | F9: 1ª | G9: GERENTE DE PROJETO | H9: Pessoas | I9: -
B10: 1B | C10: FORMAÇÃO DA EQUIPE DO PROJETO | D10: 1A | E10: 1 | F10: 1ª | G10: GERENTE DE PROJETO | H10: Pessoas | I10: -
B11: 1C | C11: IDENTIFICAÇÃO DOS STAKEHOLDERS | D11: 1A | E11: 1 | F11: 1ª | G11: GERENTE DE PROJETO | H11: Pessoas
B12: 1E | C12: REUNIÃO DE KICK-OFF | D12: 1A | E12: 1 | F12: 1ª | G12: GERENTE DE PROJETO | H12: Pessoas
B13: 2A | C13: LEVANTAMENTO DE REQUISITOS | D13: 1A | E13: 2 | F13: 2ª | G13: GERENTE DE PROJETO | H13: Pessoas | I13: -
B14: 2B | C14: ENTREVISTAS COM CANNOLI E RESTAURANTES | D14: 2A | E14: 2 | F14: 2ª | G14: GERENTE DE PROJETO | H14: Pessoas | I14: -
B15: 2C | C15: DOCUMENTAÇÃO DE REQUISITOS FUNCIONAIS | D15: 2A | E15: 2 | F15: 1ª | G15: GERENTE DE PROJETO | H15: Pessoas | I15: -
B16: 2D | C16: DOCUMENTAÇÃO DE REQUISITOS NÃO FUNCIONAIS | D16: 2A | E16: 2 | F16: 1ª | G16: GERENTE DE PROJETO | H16: Pessoas | I16: -
B17: 2E | C17: DEFINIÇÃO DO ESCOPO DETALHADO (LIMITES, PREMISSAS, RESTRIÇÕES) | D17: 2B,2C,2D | E17: 1 | F17: 2ª | G17: GERENTE DE PROJETO | H17: Pessoas | I17: -
B18: 2F | C18: CRONOGRAMA E MARCOS DO PROJETO | D18: 2B,2C,2D | E18: 1 | F18: 1ª | G18: GERENTE DE PROJETO | H18: Pessoas | I18: -
B19: 2G | C19: PLANEJAMENTO DE SEGURANÇA E LGPD | D19: 2B,2C,2D | E19: 1 | F19: 1ª | G19: GERENTE DE PROJETO | H19: Pessoas | I19: -
B20: 3A | C20: UX – EXPERIÊNCIA DO USUÁRIO | D20: 2A | E20: 1 | F20: 1ª | G20: DESIGN | H20: Pessoas + software | I20: -
B21: 3B | C21: DEFINIÇÃO DE PERSONAS (ADMIN / RESTAURANTE) | D21: 3A | E21: 1 | F21: 1ª | G21: DESIGN | H21: Pessoas + software | I21: -
B22: 3C | C22: JORNADA DO USUÁRIO | D22: 3A | E22: 1 | F22: 1ª | G22: DESIGN | H22: Pessoas + software | I22: -
B23: 3D | C23: UI – INTERFACE DO USUÁRIO | D23: 3A | E23: 1 | F23: 2ª | G23: DESIGN | H23: Pessoas + software | I23: -
B24: 3E | C24: DEFINIÇÃO DE PALETA DE CORES E TIPOGRAFIA | D24: 3D | E24: 1 | F24: 2ª | G24: DESIGN | H24: Pessoas + software | I24: -
... B49: 5E | C49: ATUALIZAÇÃO EM TEMPO REAL (OU SIMULAÇÃO) | D49: 5D | E49: 3 | F49: 2ª | G49: DESENVOLVIMENTO | H49: Pessoas + software + hardware | I49: -
B50: 6A | C50: TESTES UNITÁRIOS (CÓDIGO E MÓDULOS) | D50: 5E | E50: 3 | F50: 2ª | G50: DESENVOLVIMENTO | H50: Pessoas + software + hardware
B51: 6B | C51: TESTES INTEGRADOS (ETL + DASHBOARD + CHATBOT) | D51: 6A | E51: 3 | F51: 2ª | G51: DESENVOLVIMENTO | H51: Pessoas + software + hardware
B52: 6C | C52: TESTES DE SEGURANÇA (LGPD, CRIPTOGRAFIA, LOGIN) | D52: 6B | E52: 3 | F52: 2ª | G52: DESENVOLVIMENTO | H52: Pessoas + software + hardware
B53: 6D | C53: TESTES DE USABILIDADE E RESPONSIVIDADE | D53: 6C | E53: 3 | F53: 2ª | G53: DESENVOLVIMENTO | H53: Pessoas + software + hardware
B54: 6E | C54: HOMOLOGAÇÃO COM A CANNOLI | D54: 6D | E54: 1 | F54: 2ª | G54: EQUIPE TÉCNICA | H54: Pessoas
B55: 6F | C55: VALIDAÇÃO COM RESTAURANTES PARCEIROS | D55: 6E | E55: 1 | F55: 2ª | G55: EQUIPE TÉCNICA | H55: Pessoas
B56: 6G | C56: TREINAMENTO DE STAKEHOLDERS | D56: 6F | E56: 1 | F56: 2ª | G56: EQUIPE TÉCNICA | H56: Pessoas
B57: 7A | C57: DEPLOY DA SOLUÇÃO NA NUVEM | D57: 6G | E57: 1 | F57: 2ª | G57: EQUIPE TÉCNICA | H57: Pessoas
B58: 7B | C58: ENTREGA OFICIAL DA SOLUÇÃO | D58: 7A | E58: 1 | F58: 2ª | G58: EQUIPE TÉCNICA | H58: Pessoas
B59: 7C | C59: COLETA DE FEEDBACK INICIAL | D59: 7B | E59: 1 | F59: 2ª | G59: EQUIPE TÉCNICA | H59: Pessoas
B60: 7D | C60: RELATÓRIO FINAL DO PROJETO | D60: 7C | E60: 1 | F60: 2ª | G60: EQUIPE TÉCNICA | H60: Pessoas
B61: 7E | C61: DOCUMENTAÇÃO COMPLETA | D61: 7D | E61: 1 | F61: 2ª | G61: EQUIPE TÉCNICA | H61: Pessoas
B62: 7F | C62: AVALIAÇÃO DE RESULTADOS | D62: 7E | E62: 1 | F62: 2ª | G62: EQUIPE TÉCNICA | H62: Pessoas

Sheet Análise do Stakeholder
A8: Entregas do Projeto | B8: A definir | C8: Atulizado Em | D8: 45916
A10: SAM | I10: SRM
A11: Stakeholder | B11: Objetivos | C11: Metas | D11: Motivações e Interesses | E11: Poder e influência | F11: Importância e Impacto | G11: Papéis & Responsabilidades | H11: Sintonia "fina" | I11: Área de Interesse | J11: Nível de Detalhe | K11: Formato | L11: Frequência | M11: Mecanismo de Entrega
A12: Cliente (Usuários Finais) Cannoli | B12: Ter visibilidade das ações de marketing implementadas | C12: Controle total de ações e impactos nos consuidores | D12: Clareza nas informações | E12: Influenciam o sucesso do dashboard por meio do uso e feedback. | F12: Cruciais para a aceitação e popularidade do dashboard. | G12: Usar o dashboard, fornecer feedback, compartilhar experiências. | H12: Garantir que o dashboard atenda às suas necessidades. | I12: Relatórios sobre atualizações de recursos, melhorias com base no feedback dos usuários, dicas de uso do aplicativo. | J12: Relatórios concisos e informativos, destacando as principais entregas. | K12: Comunicar funções do produto via apresentação | L12: Entrega única
A13: Product Owner | B13: Desenvolver um aplicativo bem-sucedido que atenda às necessidades da Cannoli. | C13: Entrega de dashboard funcional que atenda as necessiades de controle da Cannoli | D13: Inovação na exposição de dados. | E13: Determina a direção e as prioridades do desenvolvimento. | F13: Fundamental para o sucesso do aplicativo. | G13: Definir a visão do produto, priorizar recursos, tomar decisões estratégicas. | H13: Alinhar o desenvolvimento com as necessidades das entregas. | I13: Relatórios de desempenho do aplicativo, métricas-chave, status do desenvolvimento. | J13: Relatórios detalhados com métricas específicas e análise de tendências. | K13: Reuniões semanal de revisão de entregas. | L13: Dailys durante a sprint e as demais reuniões do scrum. | M13: Reuniões remotas, e presenciais e manutenção do github board.
A14: Desenvolvedores | B14: Criar um da funcional e confiável. | C14: Criar a ferramenta e garantir a boa funcionalidade da mesma | D14: Desenvolvimento de dashboard e pipelines de dados. | E14: Impactam diretamente na definição de tecnologias implementadas no produto. | F14: Contribuem para a usabilidade e confiabilidade do dashboard. | G14: Escrever código, realizar testes, resolver problemas técnicos. | H14: Colaboração eficaz com o Product Owner para implementar recursos necessários com sucesso. | I14: Atualizações de prioridades de desenvolvimento, correções de bugs, novos recursos planejados. | J14: Comunicados claros e específicos sobre o que precisa ser desenvolvido. | K14: Alinhamentos semanais de sprint com a equipe de desenvolvimento e produto. | L14: Dailys durante a sprint e as demais reuniões do scrum. | M14: Reuniões virtuais, quadro de tarefas online no github.
A15: Restaurantes Parceiros | B15: Ter relatórios claros e confiaveis para auxiliar na tomada de decisão e gestão | C15: Mensurar com precisão as interações dos clietes (visitas, compras) e ter acesso transparente aos dados. | D15: Melhorar a gestão do negócio e entender o comportamento dos consumidores para aumentar a competitividade. | E15: São os usuários finais e fornecedores de dados. | F15: Solução é criada para atender as suas necessidades. A satisfação deles valida o sucesso do projeto. | G15: Utilizar os relatórios para avaliar o impacto da aplicação. | I15: Benefício da ferramenta, como usar o dash e fomo fornecer informações complementares. | J15: Direto, claro e focado no uso do dashboard | K15: Manuais e treinamentos. | L15: conforme às entregas definidas | M15: Via web.
A16: Patrocinadores | B16: Garantir que o projeto seja entregue com sucesso e que o investimento seja bem utilizado | C16: Ver o projeto sendo entregue conforme o planejado. | D16: Sucesso da solução e potencial futuro. | E16: Fornecem os recursos financeiros. | F16: Apoio na contrução de estruturas físicas de apresentação do projeto. | G16: Prover recursos. | H16: Validar retorno conforme as expectativas iniciais. | I16: Status geral do projeto. | J16: Avaliação de KPIs | K16: Apresentação de Status | L16: Mensal/ a cada entrega. | M16: Reuniões virtuais e ou presenciais.

Sheet REDE PERT
C3: Ref | D3: Etapas – Atividades - | E3: Dependência | F3: Duração em semanas
C4: 1A | D4: DEFINIÇÃO DOS OBJETIVOS DO PROJETO | F4: 1
C5: 1B | D5: FORMAÇÃO DA EQUIPE DO PROJETO | E5: 1A | F5: 1
C6: 1C | D6: IDENTIFICAÇÃO DOS STAKEHOLDERS | E6: 1A | F6: 1
C7: 1E | D7: REUNIÃO DE KICK-OFF | E7: 1A | F7: 1
C8: 2A | D8: LEVANTAMENTO DE REQUISITOS | E8: 1A | F8: 2
C9: 2B | D9: ENTREVISTAS COM CANNOLI E RESTAURANTES | E9: 2A | F9: 2
C10: 2C | D10: DOCUMENTAÇÃO DE REQUISITOS FUNCIONAIS | E10: 2A | F10: 2
C11: 2D | D11: DOCUMENTAÇÃO DE REQUISITOS NÃO FUNCIONAIS | E11: 2A | F11: 2
C12: 2E | D12: DEFINIÇÃO DO ESCOPO DETALHADO (LIMITES, PREMISSAS, RESTRIÇÕES) | E12: 2B,2C,2D | F12: 1
C13: 2F | D13: CRONOGRAMA E MARCOS DO PROJETO | E13: 2B,2C,2D | F13: 1
C14: 2G | D14: PLANEJAMENTO DE SEGURANÇA E LGPD | E14: 2B,2C,2D | F14: 1
C15: 3A | D15: UX – EXPERIÊNCIA DO USUÁRIO | E15: 2A | F15: 1
C16: 3B | D16: DEFINIÇÃO DE PERSONAS (ADMIN / RESTAURANTE) | E16: 3A | F16: 1
... C57: 7F | D57: AVALIAÇÃO DE RESULTADOS | E57: 7E | F57: 1

Sheet Gestão de Custo
B2: Previsões de Orçamento | J2: Saúde e Bem Estar
C4: 1 | D4: Capa | F4: Instruções, Histórico de Alterações e as Aprovações
C5: =C4+1 -> 2 | D5: Orçado | F5: Detalhamento dos investimentos orçados
C6: =C5+1 -> 3 | D6: Realizado | F6: Detalhamento dos investimentos realizados
C7: =C6+1 -> 4 | D7: Status | F7: Status comparando Orçado x Realizado
C8: =C7+1 -> 5 | D8: Parâmetros | F8: Parâmetros usados nas outras abas da planilha.
D10: Fonte | E10: https://escritoriodeprojetos.com.br/download/previsoes-do-orcamento/
B14: Controle de Versões
B15: Versão | C15: Data | D15: Autor | E15: Notas da Revisão
B16: 1
B17: 2
B20: Instruções | D20: =TODAY() -> 45971
B21: Ref. | C21: Aba | D21: Respons | E21: Passos
B22: 0 | C22: Param | D22: PMO | E22: Entre com o Custo do Capital
B23: 1 | C23: Orçado | D23: Gerente de Projetos | E23: Preencher as informações de identificação do projeto (Nome, Solicitante e Patrocionador)
B24: =B23+1 -> 2 | C24: Orçado | D24: Gerente de Projetos | E24: Preencher na coluna B o nome de cada Gasto (B7, B10, ...). No máximo 5, caso tiver mais de 5 agrupar os benefícios ou ajustar planilha. Veja na Aba Param - Coluna C - Tipos de gastos comuns em projetos
B25: =B24+1 -> 3 | C25: Orçado | D25: Gerente de Projetos | E25: Sempre que possível, esclareça como foi calculado o valor dos gastos (C7, C10, ...)
B26: =B25+1 -> 4 | C26: Orçado | D26: Gerente de Projetos | E26: Entrar com o valor dos gastos por ano (D9..M21), se preferir, entre com o valor do crescimento por ano (D8..M20) para todos os gastos
B27: =B26+1 -> 5 | C27: Orçado | D27: Gerente de Projetos | E27: Preenche na coluna B o nome dos custos (B29, B30)
B28: =B27+1 -> 6 | C28: Orçado | D28: Gerente de Projetos | E28: Sempre que possível, esclareça como foi calculado o valor dos custos (C29, C30)
B29: =B28+1 -> 7 | C29: Orçado | D29: Gerente de Projetos | E29: Entrar com o valor dos custos por ano (D27..M31)
B30: =B29+1 -> 8 | C30: Realizado | D30: Gerente de Projetos | E30: Entre com o valor realizado mês a mês. Caso não necessitar registrar os detalhes, pode incluir o valor total na linha 39 [Investimento total]
B31: =B30+1 -> 9
B32: =B31+1 -> 10
B33: =B32+1 -> 11
B34: =B33+1 -> 12
B36: Aprovações
B37: Ref. | C37: Data | D37: Participante | E37: Assinatura
B38: 1
B39: 2
B40: 3

Sheet Orcado
B2: Identificação do Projeto | D2: Mês
B3: Nome do Projeto | C3: =Param!C17 -> PI ADS4 - 2025 | E3: =Param!C18 -> 45891 | F3: =DATE(YEAR(E3),MONTH(E3)+1,DAY(E3)) -> 45922 | G3: =DATE(YEAR(F3),MONTH(F3)+1,DAY(F3)) -> 45952 | H3: =DATE(YEAR(G3),MONTH(G3)+1,DAY(G3)) -> 45983 | I3: =DATE(YEAR(H3),MONTH(H3)+1,DAY(H3)) -> 46013 | J3: =DATE(YEAR(I3),MONTH(I3)+1,DAY(I3)) -> 46044 | K3: =DATE(YEAR(J3),MONTH(J3)+1,DAY(J3)) -> 46075 | L3: =DATE(YEAR(K3),MONTH(K3)+1,DAY(K3)) -> 46103 | M3: =DATE(YEAR(L3),MONTH(L3)+1,DAY(L3)) -> 46134 | ... P3: =DATE(YEAR(O3),MONTH(O3)+1,DAY(O3)) -> 46225 | Q3: TOTAL
B4: Patrocinador | C4: =Param!C19 -> Cannoli | D4: 0 | E4: 1 | F4: =E4+1 -> 2 | G4: =F4+1 -> 3 | H4: =G4+1 -> 4 | I4: =H4+1 -> 5 | J4: =I4+1 -> 6 | K4: =J4+1 -> 7 | L4: =K4+1 -> 8 | M4: =L4+1 -> 9 | ... P4: =O4+1 -> 12
B5: Investimento inicial Total | C5: 110000 | D5: =SUM(D9+D11+D13+D15+D17+D19+D21+D23+D25+D27+D29) -> 110000 | E5: =SUM(E33:E46)+E9+E11+E13+E15+E17+E19+E21+E23+E25+E27+E29 -> 10388.23 | F5: =SUM(F33:F46)+F9+F11+F13+F15+F17+F19+F21+F23+F25+F27 -> 10305.458 | G5: =SUM(G33:G46)+G9+G11+G13+G15+G17+G19+G21+G23+G25+G27 -> 7986.0038 | H5: =SUM(H33:H46)+H9+H11+H13+H15+H17+H19+H21+H23+H25+H27 -> 8234.6042 | I5: =SUM(I33:I46)+I9+I11+I13+I15+I17+I19+I21+I23+I25+I27 -> 9058.0646 | J5: =SUM(J33:J46)+J9+J11+J13+J15+J17+J19+J21+J23+J25+J27 -> 9963.8711 | K5: =SUM(K33:K46)+K9+K11+K13+K15+K17+K19+K21+K23+K25+K27 -> 10960.258 | L5: =SUM(L33:L46)+L9+L11+L13+L15+L17+L19+L21+L23+L25+L27 -> 12056.284 | M5: =SUM(M33:M46)+M9+M11+M13+M15+M17+M19+M21+M23+M25+M27 -> 13261.912 | ... P5: =SUM(P33:P46)+P9+P11+P13+P15+P17+P19+P21+P23+P25+P27 -> 17651.605 | Q5: =SUM(D5:P5) -> 250501.31
B6: Investimento Acumulado | C6: 0 | D6: =D5 -> 110000 | E6: =D6+E5 -> 120388.23 | F6: =E6+F5 -> 130693.69 | G6: =F6+G5 -> 138679.69 | H6: =G6+H5 -> 146914.3 | I6: =H6+I5 -> 155972.36 | J6: =I6+J5 -> 165936.23 | K6: =J6+K5 -> 176896.49 | L6: =K6+L5 -> 188952.77 | ... P6: =O6+P5 -> 250501.31
B7: Orçado | C7: Explicação
B8: Investimento c/ taxa de crescimento | C8: Para facilitar o cálculo do gasto baseado em uma taxa de crescimento.
B9: Iniciação | C9: Gasto referente ao start do projeto, desde o estudo, mapeamento de funcionalidade e formação de time | D9: 10000 | E9: 3500 | F9: =E9*(1+F8) -> 3500 | G9: 500 | H9: 0 | I9: =H9*(1+I8) -> 0 | J9: =I9*(1+J8) -> 0 | K9: =J9*(1+K8) -> 0 | L9: =K9*(1+L8) -> 0 | M9: =L9*(1+M8) -> 0 | N9: =M9*(1+N8) -> 0 | O9: =N9*(1+O8) -> 0 | P9: =O9*(1+P8) -> 0 | Q9: =SUM(E9:P9) -> 7500
B10: Taxa de Crescimento de 10% | C10: Taxa de crescimento de investimento de 10% ao mês MOM | F10: 0.1 | G10: =F10 -> 0.1 | H10: =G10 -> 0.1 | I10: =H10 -> 0.1 | J10: =I10 -> 0.1 | K10: =J10 -> 0.1 | L10: =K10 -> 0.1 | M10: =L10 -> 0.1 | N10: =M10 -> 0.1 | ... P10: =O10 -> 0.1
B11: Planejamento | C11: Tudo que tange o mapeamento inicial do planejamento, como plano de exercicio e requisitos, mapas de academias e parques e afins. | D11: 12000 | E11: 794.96 | F11: =E11*(1+F10) -> 874.456 | G11: =F11*(1+G10) -> 961.9016 | H11: =G11*(1+H10) -> 1058.0918 | I11: =H11*(1+I10) -> 1163.9009 | J11: =I11*(1+J10) -> 1280.291 | K11: =J11*(1+K10) -> 1408.3201 | L11: =K11*(1+L10) -> 1549.1521 | M11: =L11*(1+M10) -> 1704.0674 | ... P11: =O11*(1+P10) -> 2268.1137 | Q11: =SUM(E11:P11) -> 16999.65
B12: Taxa de Crescimento de 10% | C12: Taxa de crescimento de investimento de 10% ao mês MOM | F12: 0.1 | G12: =F12 -> 0.1 | H12: =G12 -> 0.1 | I12: =H12 -> 0.1 | J12: =I12 -> 0.1 | K12: =J12 -> 0.1 | L12: =K12 -> 0.1 | M12: =L12 -> 0.1 | N12: =M12 -> 0.1 | ... P12: =O12 -> 0.1
B13: Design e Prototipagem | C13: Todo processo que compete ao desenvolvimento da funcionalidade em sua camada de Wire, Layout, experiência, ou seja, UX. | D13: 16000 | E13: 617.29 | F13: =E13*(1+F12) -> 679.019 | G13: =F13*(1+G12) -> 746.9209 | H13: =G13*(1+H12) -> 821.61299 | I13: =H13*(1+I12) -> 903.77429 | J13: =I13*(1+J12) -> 994.15172 | K13: =J13*(1+K12) -> 1093.5669 | L13: =K13*(1+L12) -> 1202.9236 | M13: =L13*(1+M12) -> 1323.2159 | ... P13: =O13*(1+P12) -> 1761.2004 | Q13: =SUM(E13:P13) -> 13200.305
B14: Taxa de Crescimento de 10% | C14: Taxa de crescimento de investimento de 10% ao mês MOM | F14: 0.1 | G14: =F14 -> 0.1 | H14: =G14 -> 0.1 | I14: =H14 -> 0.1 | J14: =I14 -> 0.1 | K14: =J14 -> 0.1 | L14: =K14 -> 0.1 | M14: =L14 -> 0.1 | N14: =M14 -> 0.1 | ... P14: =O14 -> 0.1
B15: Desenvolvimento | C15: Desenvolvimento do frontend, backend e todo processo de desenvolvimento. | D15: 40000 | E15: 1496.43 | F15: =E15*(1+F14) -> 1646.073 | G15: =F15*(1+G14) -> 1810.6803 | H15: =G15*(1+H14) -> 1991.7483 | I15: =H15*(1+I14) -> 2190.9232 | J15: =I15*(1+J14) -> 2410.0155 | K15: =J15*(1+K14) -> 2651.017 | L15: =K15*(1+L14) -> 2916.1187 | M15: =L15*(1+M14) -> 3207.7306 | ... P15: =O15*(1+P14) -> 4269.4894 | Q15: =SUM(E15:P15) -> 32000.084
B16: Taxa de Crescimento de 10% | C16: Taxa de crescimento de investimento de 10% ao mês MOM | F16: 0.1 | G16: =F16 -> 0.1 | H16: =G16 -> 0.1 | I16: =H16 -> 0.1 | J16: =I16 -> 0.1 | K16: =J16 -> 0.1 | L16: =K16 -> 0.1 | M16: =L16 -> 0.1 | N16: =M16 -> 0.1 | ... P16: =O16 -> 0.1
B17: Integração com sistemas de monitoramento de saúde | C17: Foco na segurança e integração da plataforma. | D17: 6000 | E17: 233.8 | F17: =E17*(1+F16) -> 257.18 | G17: =F17*(1+G16) -> 282.898 | H17: =G17*(1+H16) -> 311.1878 | I17: =H17*(1+I16) -> 342.30658 | J17: =I17*(1+J16) -> 376.53724 | K17: =J17*(1+K16) -> 414.19096 | L17: =K17*(1+L16) -> 455.61006 | M17: =L17*(1+M16) -> 501.17106 | ... P17: =O17*(1+P16) -> 667.05869 | Q17: =SUM(E17:P17) -> 4999.6455
B18: Taxa de Crescimento de 10% | C18: Taxa de crescimento de investimento de 10% ao mês MOM | F18: 0.1 | G18: =F18 -> 0.1 | H18: =G18 -> 0.1 | I18: =H18 -> 0.1 | J18: =I18 -> 0.1 | K18: =J18 -> 0.1 | L18: =K18 -> 0.1 | M18: =L18 -> 0.1 | N18: =M18 -> 0.1 | ... P18: =O18 -> 0.1
B19: Teste | C19: Verificar as funcionalidades, realizar testes e possíveis correções | D19: 12000 | E19: 542.45 | F19: =E19*(1+F18) -> 596.695 | G19: =F19*(1+G18) -> 656.3645 | H19: =G19*(1+H18) -> 722.00095 | I19: =H19*(1+I18) -> 794.20105 | J19: =I19*(1+J18) -> 873.62115 | K19: =J19*(1+K18) -> 960.98326 | L19: =K19*(1+L18) -> 1057.0816 | M19: =L19*(1+M18) -> 1162.7897 | ... P19: =O19*(1+P18) -> 1547.6732 | Q19: =SUM(E19:P19) -> 11599.905
B20: Taxa de Crescimento de 10% | C20: Taxa de crescimento de investimento de 10% ao mês MOM | F20: 0.1 | G20: =F20 -> 0.1 | H20: =G20 -> 0.1 | I20: =H20 -> 0.1 | J20: =I20 -> 0.1 | K20: =J20 -> 0.1 | L20: =K20 -> 0.1 | M20: =L20 -> 0.1 | N20: =M20 -> 0.1 | ... P20: =O20 -> 0.1
B21: Lançamento (Stakeholders internos) | C21: Tudo que tange aos stakeholders | D21: 4000 | E21: 869.8 | F21: =E21*(1+F20) -> 956.78 | G21: =F21*(1+G20) -> 1052.458 | H21: =G21*(1+H20) -> 1157.7038 | I21: =H21*(1+I20) -> 1273.4742 | J21: =I21*(1+J20) -> 1400.8216 | K21: =J21*(1+K20) -> 1540.9038 | L21: =K21*(1+L20) -> 1694.9941 | M21: =L21*(1+M20) -> 1864.4935 | ... P21: =O21*(1+P20) -> 2481.6409 | Q21: =SUM(E21:P21) -> 18600.05
B22: Taxa de Crescimento de 10% | C22: Taxa de crescimento de investimento de 10% ao mês MOM | F22: 0.1 | G22: =F22 -> 0.1 | H22: =G22 -> 0.1 | I22: =H22 -> 0.1 | J22: =I22 -> 0.1 | K22: =J22 -> 0.1 | L22: =K22 -> 0.1 | M22: =L22 -> 0.1 | N22: =M22 -> 0.1 | ... P22: =O22 -> 0.1
B23: Pós-lançamento (Stakeholders internos) | C23: Tudo que tange o pós lançamento. | D23: 3000 | E23: 514.4 | F23: =E23*(1+F22) -> 565.84 | G23: =F23*(1+G22) -> 622.424 | H23: =G23*(1+H22) -> 684.6664 | I23: =H23*(1+I22) -> 753.13304 | J23: =I23*(1+J22) -> 828.44634 | K23: =J23*(1+K22) -> 911.29098 | L23: =K23*(1+L22) -> 1002.4201 | M23: =L23*(1+M22) -> 1102.6621 | ... P23: =O23*(1+P22) -> 1467.6432 | Q23: =SUM(E23:P23) -> 11000.076
B24: Taxa de Crescimento de 10% | C24: Taxa de crescimento de investimento de 10% ao mês MOM | F24: 0.1 | G24: =F24 -> 0.1 | H24: =G24 -> 0.1 | I24: =H24 -> 0.1 | J24: =I24 -> 0.1 | K24: =J24 -> 0.1 | L24: =K24 -> 0.1 | M24: =L24 -> 0.1 | N24: =M24 -> 0.1 | ... P24: =O24 -> 0.1
B25: Marketing e Divulgação - para o Mercado | C25: Todo processo de marketing e divulgação. | D25: 2000 | E25: 701.45 | F25: =E25*(1+F24) -> 771.595 | G25: =F25*(1+G24) -> 848.7545 | H25: =G25*(1+H24) -> 933.62995 | I25: =H25*(1+I24) -> 1026.9929 | J25: =I25*(1+J24) -> 1129.6922 | K25: =J25*(1+K24) -> 1242.6615 | L25: =K25*(1+L24) -> 1366.9276 | M25: =L25*(1+M24) -> 1503.6204 | ... P25: =O25*(1+P24) -> 2001.3187 | Q25: =SUM(E25:P25) -> 15000.006
B26: Taxa de Crescimento de 10% | C26: Taxa de crescimento de investimento de 10% ao mês MOM | F26: 0.1 | G26: =F26 -> 0.1 | H26: =G26 -> 0.1 | I26: =H26 -> 0.1 | J26: =I26 -> 0.1 | K26: =J26 -> 0.1 | L26: =K26 -> 0.1 | M26: =L26 -> 0.1 | N26: =M26 -> 0.1 | ... P26: =O26 -> 0.1
B27: Avaliação e Aperfeiçoamento | C27: Feedback e adapção | D27: 3000 | E27: 416.2 | F27: =E27*(1+F26) -> 457.82 | G27: =F27*(1+G26) -> 503.602 | H27: =G27*(1+H26) -> 553.9622 | I27: =H27*(1+I26) -> 609.35842 | J27: =I27*(1+J26) -> 670.29426 | K27: =J27*(1+K26) -> 737.32369 | L27: =K27*(1+L26) -> 811.05606 | M27: =L27*(1+M26) -> 892.16166 | ... P27: =O27*(1+P26) -> 1187.4672 | Q27: =SUM(E27:P27) -> 8900.1389
B28: Taxa de Crescimento de 10% | C28: Taxa de crescimento de investimento de 10% ao mês MOM | F28: 0.1 | G28: =F28 -> 0.1 | H28: =G28 -> 0.1 | I28: =H28 -> 0.1 | J28: =I28 -> 0.1 | K28: =J28 -> 0.1 | L28: =K28 -> 0.1 | M28: =L28 -> 0.1 | N28: =M28 -> 0.1 | ... P28: =O28 -> 0.1
B29: Expansão | C29: Feedback e adapção | D29: 2000 | E29: 701.45 | F29: =E29*(1+F28) -> 771.595 | G29: =F29*(1+G28) -> 848.7545 | H29: =G29*(1+H28) -> 933.62995 | I29: =H29*(1+I28) -> 1026.9929 | J29: =I29*(1+J28) -> 1129.6922 | K29: =J29*(1+K28) -> 1242.6615 | L29: =K29*(1+L28) -> 1366.9276 | M29: =L29*(1+M28) -> 1503.6204 | ... P29: =O29*(1+P28) -> 2001.3187 | Q29: =SUM(E29:P29) -> 15000.006
B32: Investimentos
B33: Custo de Implementação | D33: 0 | E33: 0 | F33: =E33 -> 0 | G33: =F33 -> 0 | H33: =G33 -> 0 | I33: =H33 -> 0 | J33: =I33 -> 0 | K33: =J33 -> 0 | L33: =K33 -> 0 | M33: =L33 -> 0 | ... P33: =O33 -> 0 | Q33: =SUM(D33:P33) -> 0
B34: Custo da Operação | F34: =E34 -> 0 | G34: =F34 -> 0 | H34: =G34 -> 0 | I34: =H34 -> 0 | J34: =I34 -> 0 | K34: =J34 -> 0 | L34: =K34 -> 0 | M34: =L34 -> 0 | ... P34: =O34 -> 0 | Q34: =SUM(D34:P34) -> 0
B35: Custos de Treinamento | F35: =E35 -> 0 | G35: =F35 -> 0 | H35: =G35 -> 0 | I35: =H35 -> 0 | J35: =I35 -> 0 | K35: =J35 -> 0 | L35: =K35 -> 0 | M35: =L35 -> 0 | ... P35: =O35 -> 0 | Q35: =SUM(D35:P35) -> 0
B36: Custo | F36: =E36 -> 0 | G36: =F36 -> 0 | H36: =G36 -> 0 | I36: =H36 -> 0 | J36: =I36 -> 0 | K36: =J36 -> 0 | L36: =K36 -> 0 | M36: =L36 -> 0 | ... P36: =O36 -> 0 | Q36: =SUM(D36:P36) -> 0
B37: Custo | F37: =E37 -> 0 | G37: =F37 -> 0 | H37: =G37 -> 0 | I37: =H37 -> 0 | J37: =I37 -> 0 | K37: =J37 -> 0 | L37: =K37 -> 0 | M37: =L37 -> 0 | ... P37: =O37 -> 0 | Q37: =SUM(D37:P37) -> 0
B38: Custo | F38: =E38 -> 0 | G38: =F38 -> 0 | H38: =G38 -> 0 | I38: =H38 -> 0 | J38: =I38 -> 0 | K38: =J38 -> 0 | L38: =K38 -> 0 | M38: =L38 -> 0 | ... P38: =O38 -> 0 | Q38: =SUM(D38:P38) -> 0
B39: Custo | F39: =E39 -> 0 | G39: =F39 -> 0 | H39: =G39 -> 0 | I39: =H39 -> 0 | J39: =I39 -> 0 | K39: =J39 -> 0 | L39: =K39 -> 0 | M39: =L39 -> 0 | ... P39: =O39 -> 0 | Q39: =SUM(D39:P39) -> 0
B40: Custo | F40: =E40 -> 0 | G40: =F40 -> 0 | H40: =G40 -> 0 | I40: =H40 -> 0 | J40: =I40 -> 0 | K40: =J40 -> 0 | L40: =K40 -> 0 | M40: =L40 -> 0 | ... P40: =O40 -> 0 | Q40: =SUM(D40:P40) -> 0
B41: Custo | F41: =E41 -> 0 | G41: =F41 -> 0 | H41: =G41 -> 0 | I41: =H41 -> 0 | J41: =I41 -> 0 | K41: =J41 -> 0 | L41: =K41 -> 0 | M41: =L41 -> 0 | ... P41: =O41 -> 0 | Q41: =SUM(D41:P41) -> 0
B42: Custo | F42: =E42 -> 0 | G42: =F42 -> 0 | H42: =G42 -> 0 | I42: =H42 -> 0 | J42: =I42 -> 0 | K42: =J42 -> 0 | L42: =K42 -> 0 | M42: =L42 -> 0 | ... P42: =O42 -> 0 | Q42: =SUM(D42:P42) -> 0
B43: Custo | F43: =E43 -> 0 | G43: =F43 -> 0 | H43: =G43 -> 0 | I43: =H43 -> 0 | J43: =I43 -> 0 | K43: =J43 -> 0 | L43: =K43 -> 0 | M43: =L43 -> 0 | ... P43: =O43 -> 0 | Q43: =SUM(D43:P43) -> 0
B44: Custo | F44: =E44 -> 0 | G44: =F44 -> 0 | H44: =G44 -> 0 | I44: =H44 -> 0 | J44: =I44 -> 0 | K44: =J44 -> 0 | L44: =K44 -> 0 | M44: =L44 -> 0 | ... P44: =O44 -> 0 | Q44: =SUM(D44:P44) -> 0
B45: Custo | F45: =E45 -> 0 | G45: =F45 -> 0 | H45: =G45 -> 0 | I45: =H45 -> 0 | J45: =I45 -> 0 | K45: =J45 -> 0 | L45: =K45 -> 0 | M45: =L45 -> 0 | ... P45: =O45 -> 0 | Q45: =SUM(D45:P45) -> 0
B46: Outros custos | F46: =E46 -> 0 | G46: =F46 -> 0 | H46: =G46 -> 0 | I46: =H46 -> 0 | J46: =I46 -> 0 | K46: =J46 -> 0 | L46: =K46 -> 0 | M46: =L46 -> 0 | ... P46: =O46 -> 0 | Q46: =SUM(D46:P46) -> 0
B51: Indicadores Financeiros
B53: NPV/VPL | D53: =NPV(Param!D4,E5:P5)+D5 -> 204067.37
B54: Payback | D54: =COUNTIF(D6:P6,"<=0") -> 0
B55: ROI | D55: =SUM(E5:P5)/-D5 -> -1.2772846

Sheet Realizado
B2: =Orcado!B2 -> Identificação do Projeto | E2: Mês
B3: Nome do Projeto | C3: =Param!C17 -> PI ADS4 - 2025 | E3: =Orcado!E3 -> 45891 | F3: =Orcado!F3 -> 45922 | G3: =Orcado!G3 -> 45952 | H3: =Orcado!H3 -> 45983 | I3: =Orcado!I3 -> 46013 | J3: =Orcado!J3 -> 46044 | K3: =Orcado!K3 -> 46075 | L3: =Orcado!L3 -> 46103 | ... P3: =Orcado!P3 -> 46225 | Q3: TOTAL
B4: Patrocinador | C4: =Param!C19 -> Cannoli | D4: 0 | E4: 1 | F4: =E4+1 -> 2 | G4: =F4+1 -> 3 | H4: =G4+1 -> 4 | I4: =H4+1 -> 5 | J4: =I4+1 -> 6 | K4: =J4+1 -> 7 | L4: =K4+1 -> 8 | M4: =L4+1 -> 9 | ... P4: =O4+1 -> 12
B5: Investimento Total | D5: =SUM(D9+D11+D13+D15+D17+D19+D21+D23+D25+D27+D29) -> 158109 | E5: =SUM(E39:E52)+E9+E11+E13+E15+E17+E19+E21+E23+E25+E27+E29 -> 7987.4 | F5: =SUM(F9+F11+F13+F15+F17+F19+F21+F23+F25+F27+F29) -> 8708.14 | G5: =SUM(G9+G11+G13+G15+G17+G19+G21+G23+G25+G27+G29) -> 9500.954 | H5: =SUM(H9+H11+H13+H15+H17+H19+H21+H23+H25+H27+H29) -> 10373.049 | I5: =SUM(I9+I11+I13+I15+I17+I19+I21+I23+I25+I27+I29) -> 11332.354 | J5: =SUM(J9+J11+J13+J15+J17+J19+J21+J23+J25+J27+J29) -> 12387.59 | K5: =SUM(K9+K11+K13+K15+K17+K19+K21+K23+K25+K27+K29) -> 13548.349 | L5: =SUM(L9+L11+L13+L15+L17+L19+L21+L23+L25+L27+L29) -> 14825.184 | M5: =SUM(M9+M11+M13+M15+M17+M19+M21+M23+M25+M27+M29) -> 16229.702 | ... P5: =SUM(P9+P11+P13+P15+P17+P19+P21+P23+P25+P27+P29) -> 21343.553 | Q5: =SUM(E5:P5) -> 163485.09
B6: Investimento Acumulado | D6: =D5 -> 158109 | E6: =D6+E5 -> 166096.4 | F6: =E6+F5 -> 174804.54 | G6: =F6+G5 -> 184305.49 | H6: =G6+H5 -> 194678.54 | I6: =H6+I5 -> 206010.9 | J6: =I6+J5 -> 218398.49 | K6: =J6+K5 -> 231946.84 | L6: =K6+L5 -> 246772.02 | ... P6: =O6+P5 -> 321594.09
B7: Realizado | C7: Explicação
B8: Investimento c/ taxa de crescimento
B9: =Orcado!B9 -> Iniciação | C9: Gasto referente ao start do projeto, desde o estudo, mapeamento de funcionalidade e formação de time | D9: 9360 | E9: 780 | F9: =E9*(1+F8) -> 780 | G9: =F9*(1+G8) -> 780 | H9: =G9*(1+H8) -> 780 | I9: =H9*(1+I8) -> 780 | J9: =I9*(1+J8) -> 780 | K9: =J9*(1+K8) -> 780 | L9: =K9*(1+L8) -> 780 | M9: =L9*(1+M8) -> 780 | ... P9: =O9*(1+P8) -> 780 | Q9: =SUM(E9:P9) -> 9360
F10: 0.1 | G10: 0.1 | H10: 0.1 | I10: 0.1 | J10: 0.1 | K10: 0.1 | L10: 0.1 | M10: 0.1 | N10: 0.1 | O10: 0.1 | P10: 0.1
B11: =Orcado!B11 -> Planejamento | C11: Tudo que tange o mapeamento inicial do planejamento, como plano de exercicio e requisitos, mapas de academias e parques e afins. | D11: 16680 | E11: 780 | F11: =E11*(1+F10) -> 858 | G11: =F11*(1+G10) -> 943.8 | H11: =G11*(1+H10) -> 1038.18 | I11: =H11*(1+I10) -> 1141.998 | J11: =I11*(1+J10) -> 1256.1978 | K11: =J11*(1+K10) -> 1381.8176 | L11: =K11*(1+L10) -> 1519.9993 | M11: =L11*(1+M10) -> 1671.9993 | ... P11: =O11*(1+P10) -> 2225.431 | Q11: =SUM(E11:P11) -> 16679.741
F12: 0.1 | G12: =F12 -> 0.1 | H12: =G12 -> 0.1 | I12: =H12 -> 0.1 | J12: =I12 -> 0.1 | K12: =J12 -> 0.1 | L12: =K12 -> 0.1 | M12: =L12 -> 0.1 | N12: =M12 -> 0.1 | ... P12: =O12 -> 0.1
B13: =Orcado!B13 -> Design e Prototipagem | C13: Todo processo que compete ao desenvolvimento da funcionalidade em sua camada de Wire, Layout, experiência, ou seja, UX. | D13: 14969 | E13: 700 | F13: =E13*(1+F12) -> 770 | G13: =F13*(1+G12) -> 847 | H13: =G13*(1+H12) -> 931.7 | I13: =H13*(1+I12) -> 1024.87 | J13: =I13*(1+J12) -> 1127.357 | K13: =J13*(1+K12) -> 1240.0927 | L13: =K13*(1+L12) -> 1364.102 | M13: =L13*(1+M12) -> 1500.5122 | ... P13: =O13*(1+P12) -> 1997.1817 | Q13: =SUM(E13:P13) -> 14968.999
F14: 0.1 | G14: =F14 -> 0.1 | H14: =G14 -> 0.1 | I14: =H14 -> 0.1 | J14: =I14 -> 0.1 | K14: =J14 -> 0.1 | L14: =K14 -> 0.1 | M14: =L14 -> 0.1 | N14: =M14 -> 0.1 | ... P14: =O14 -> 0.1
B15: =Orcado!B15 -> Desenvolvimento | C15: Desenvolvimento do frontend, backend e todo processo de desenvolvimento. | D15: 32000 | E15: 1700 | F15: =E15*(1+F14) -> 1870 | G15: =F15*(1+G14) -> 2057 | H15: =G15*(1+H14) -> 2262.7 | I15: =H15*(1+I14) -> 2488.97 | J15: =I15*(1+J14) -> 2737.867 | K15: =J15*(1+K14) -> 3011.6537 | L15: =K15*(1+L14) -> 3312.8191 | M15: =L15*(1+M14) -> 3644.101 | ... P15: =O15*(1+P14) -> 4850.2984 | Q15: =SUM(E15:P15) -> 36353.282
F16: 0.1 | G16: =F16 -> 0.1 | H16: =G16 -> 0.1 | I16: =H16 -> 0.1 | J16: =I16 -> 0.1 | K16: =J16 -> 0.1 | L16: =K16 -> 0.1 | M16: =L16 -> 0.1 | N16: =M16 -> 0.1 | ... P16: =O16 -> 0.1
B17: =Orcado!B17 -> Integração com sistemas de monitoramento de saúde | C17: Foco na segurança e integração da plataforma. | D17: 5000 | E17: 203 | F17: =E17*(1+F16) -> 223.3 | G17: =F17*(1+G16) -> 245.63 | H17: =G17*(1+H16) -> 270.193 | I17: =H17*(1+I16) -> 297.2123 | J17: =I17*(1+J16) -> 326.93353 | K17: =J17*(1+K16) -> 359.62688 | L17: =K17*(1+L16) -> 395.58957 | M17: =L17*(1+M16) -> 435.14853 | ... P17: =O17*(1+P16) -> 579.18269 | Q17: =SUM(E17:P17) -> 4341.0096
F18: 0.1 | G18: =F18 -> 0.1 | H18: =G18 -> 0.1 | I18: =H18 -> 0.1 | J18: =I18 -> 0.1 | K18: =J18 -> 0.1 | L18: =K18 -> 0.1 | M18: =L18 -> 0.1 | N18: =M18 -> 0.1 | ... P18: =O18 -> 0.1
B19: =Orcado!B19 -> Teste | C19: Verificar as funcionalidades, realizar testes e possíveis correções | D19: 11600 | E19: 520 | F19: =E19*(1+F18) -> 572 | G19: =F19*(1+G18) -> 629.2 | H19: =G19*(1+H18) -> 692.12 | I19: =H19*(1+I18) -> 761.332 | J19: =I19*(1+J18) -> 837.4652 | K19: =J19*(1+K18) -> 921.21172 | L19: =K19*(1+L18) -> 1013.3329 | M19: =L19*(1+M18) -> 1114.6662 | ... P19: =O19*(1+P18) -> 1483.6207 | Q19: =SUM(E19:P19) -> 11119.828
F20: 0.1 | G20: =F20 -> 0.1 | H20: =G20 -> 0.1 | I20: =H20 -> 0.1 | J20: =I20 -> 0.1 | K20: =J20 -> 0.1 | L20: =K20 -> 0.1 | M20: =L20 -> 0.1 | N20: =M20 -> 0.1 | ... P20: =O20 -> 0.1
B21: =Orcado!B21 -> Lançamento (Stakeholders internos) | C21: Tudo que tange aos stakeholders | D21: 18600 | E21: 950 | F21: =E21*(1+F20) -> 1045 | G21: =F21*(1+G20) -> 1149.5 | H21: =G21*(1+H20) -> 1264.45 | I21: =H21*(1+I20) -> 1390.895 | J21: =I21*(1+J20) -> 1529.9845 | K21: =J21*(1+K20) -> 1682.983 | L21: =K21*(1+L20) -> 1851.2812 | M21: =L21*(1+M20) -> 2036.4094 | ... P21: =O21*(1+P20) -> 2710.4609 | Q21: =SUM(E21:P21) -> 20315.07
F22: 0.1 | G22: =F22 -> 0.1 | H22: =G22 -> 0.1 | I22: =H22 -> 0.1 | J22: =I22 -> 0.1 | K22: =J22 -> 0.1 | L22: =K22 -> 0.1 | M22: =L22 -> 0.1 | N22: =M22 -> 0.1 | ... P22: =O22 -> 0.1
B23: =Orcado!B23 -> Pós-lançamento (Stakeholders internos) | C23: Tudo que tange o pós lançamento. | D23: 11000 | E23: 514.4 | F23: =E23*(1+F22) -> 565.84 | G23: =F23*(1+G22) -> 622.424 | H23: =G23*(1+H22) -> 684.6664 | I23: =H23*(1+I22) -> 753.13304 | J23: =I23*(1+J22) -> 828.44634 | K23: =J23*(1+K22) -> 911.29098 | L23: =K23*(1+L22) -> 1002.4201 | M23: =L23*(1+M22) -> 1102.6621 | ... P23: =O23*(1+P22) -> 1467.6432 | Q23: =SUM(E23:P23) -> 11000.076
F24: 0.1 | G24: =F24 -> 0.1 | H24: =G24 -> 0.1 | I24: =H24 -> 0.1 | J24: =I24 -> 0.1 | K24: =J24 -> 0.1 | L24: =K24 -> 0.1 | M24: =L24 -> 0.1 | N24: =M24 -> 0.1 | ... P24: =O24 -> 0.1
B25: =Orcado!B25 -> Marketing e Divulgação - para o Mercado | C25: Todo processo de marketing e divulgação. | D25: 15000 | E25: 720 | F25: =E25*(1+F24) -> 792 | G25: =F25*(1+G24) -> 871.2 | H25: =G25*(1+H24) -> 958.32 | I25: =H25*(1+I24) -> 1054.152 | J25: =I25*(1+J24) -> 1159.5672 | K25: =J25*(1+K24) -> 1275.5239 | L25: =K25*(1+L24) -> 1403.0763 | M25: =L25*(1+M24) -> 1543.3839 | ... P25: =O25*(1+P24) -> 2054.244 | Q25: =SUM(E25:P25) -> 15396.684
F26: 0.1 | G26: =F26 -> 0.1 | H26: =G26 -> 0.1 | I26: =H26 -> 0.1 | J26: =I26 -> 0.1 | K26: =J26 -> 0.1 | L26: =K26 -> 0.1 | M26: =L26 -> 0.1 | N26: =M26 -> 0.1 | ... P26: =O26 -> 0.1
B27: =Orcado!B27 -> Avaliação e Aperfeiçoamento | C27: Feedback e adapção | D27: 8900 | E27: 410 | F27: =E27*(1+F26) -> 451 | G27: =F27*(1+G26) -> 496.1 | H27: =G27*(1+H26) -> 545.71 | I27: =H27*(1+I26) -> 600.281 | J27: =I27*(1+J26) -> 660.3091 | K27: =J27*(1+K26) -> 726.34001 | L27: =K27*(1+L26) -> 798.97401 | M27: =L27*(1+M26) -> 878.87141 | ... P27: =O27*(1+P26) -> 1169.7778 | Q27: =SUM(E27:P27) -> 8767.5563
F28: 0.1 | G28: =F28 -> 0.1 | H28: =G28 -> 0.1 | I28: =H28 -> 0.1 | J28: =I28 -> 0.1 | K28: =J28 -> 0.1 | L28: =K28 -> 0.1 | M28: =L28 -> 0.1 | N28: =M28 -> 0.1 | ... P28: =O28 -> 0.1
B29: =Orcado!B29 -> Expansão | C29: Feedback e adapção | D29: 15000 | E29: 710 | F29: =E29*(1+F28) -> 781 | G29: =F29*(1+G28) -> 859.1 | H29: =G29*(1+H28) -> 945.01 | I29: =H29*(1+I28) -> 1039.511 | J29: =I29*(1+J28) -> 1143.4621 | K29: =J29*(1+K28) -> 1257.8083 | L29: =K29*(1+L28) -> 1383.5891 | M29: =L29*(1+M28) -> 1521.9481 | ... P29: =O29*(1+P28) -> 2025.7129 | Q29: =SUM(E29:P29) -> 15182.841
B38: Investimentos
B39: =Orcado!B33 -> Custo de Implementação | D39: 0 | E39: 0 | F39: =E39 -> 0 | G39: =F39 -> 0 | H39: =G39 -> 0 | I39: =H39 -> 0 | J39: =I39 -> 0 | K39: =J39 -> 0 | L39: =K39 -> 0 | M39: =L39 -> 0 | ... P39: =O39 -> 0 | Q39: =SUM(D39:P39) -> 0
B40: =Orcado!B34 -> Custo da Operação | F40: =E40 -> 0 | G40: =F40 -> 0 | H40: =G40 -> 0 | I40: =H40 -> 0 | J40: =I40 -> 0 | K40: =J40 -> 0 | L40: =K40 -> 0 | M40: =L40 -> 0 | ... P40: =O40 -> 0 | Q40: =SUM(D40:P40) -> 0
B41: =Orcado!B35 -> Custos de Treinamento | F41: =E41 -> 0 | G41: =F41 -> 0 | H41: =G41 -> 0 | I41: =H41 -> 0 | J41: =I41 -> 0 | K41: =J41 -> 0 | L41: =K41 -> 0 | M41: =L41 -> 0 | ... P41: =O41 -> 0 | Q41: =SUM(D41:P41) -> 0
B42: =Orcado!B36 -> Custo | F42: =E42 -> 0 | G42: =F42 -> 0 | H42: =G42 -> 0 | I42: =H42 -> 0 | J42: =I42 -> 0 | K42: =J42 -> 0 | L42: =K42 -> 0 | M42: =L42 -> 0 | ... P42: =O42 -> 0 | Q42: =SUM(D42:P42) -> 0
B43: =Orcado!B37 -> Custo | F43: =E43 -> 0 | G43: =F43 -> 0 | H43: =G43 -> 0 | I43: =H43 -> 0 | J43: =I43 -> 0 | K43: =J43 -> 0 | L43: =K43 -> 0 | M43: =L43 -> 0 | ... P43: =O43 -> 0 | Q43: =SUM(D43:P43) -> 0
B44: =Orcado!B38 -> Custo | F44: =E44 -> 0 | G44: =F44 -> 0 | H44: =G44 -> 0 | I44: =H44 -> 0 | J44: =I44 -> 0 | K44: =J44 -> 0 | L44: =K44 -> 0 | M44: =L44 -> 0 | ... P44: =O44 -> 0 | Q44: =SUM(D44:P44) -> 0
B45: =Orcado!B39 -> Custo | F45: =E45 -> 0 | G45: =F45 -> 0 | H45: =G45 -> 0 | I45: =H45 -> 0 | J45: =I45 -> 0 | K45: =J45 -> 0 | L45: =K45 -> 0 | M45: =L45 -> 0 | ... P45: =O45 -> 0 | Q45: =SUM(D45:P45) -> 0
B46: =Orcado!B40 -> Custo | F46: =E46 -> 0 | G46: =F46 -> 0 | H46: =G46 -> 0 | I46: =H46 -> 0 | J46: =I46 -> 0 | K46: =J46 -> 0 | L46: =K46 -> 0 | M46: =L46 -> 0 | ... P46: =O46 -> 0 | Q46: =SUM(D46:P46) -> 0
B47: =Orcado!B41 -> Custo | F47: =E47 -> 0 | G47: =F47 -> 0 | H47: =G47 -> 0 | I47: =H47 -> 0 | J47: =I47 -> 0 | K47: =J47 -> 0 | L47: =K47 -> 0 | M47: =L47 -> 0 | ... P47: =O47 -> 0 | Q47: =SUM(D47:P47) -> 0
B48: =Orcado!B42 -> Custo | F48: =E48 -> 0 | G48: =F48 -> 0 | H48: =G48 -> 0 | I48: =H48 -> 0 | J48: =I48 -> 0 | K48: =J48 -> 0 | L48: =K48 -> 0 | M48: =L48 -> 0 | ... P48: =O48 -> 0 | Q48: =SUM(D48:P48) -> 0
B49: =Orcado!B43 -> Custo | F49: =E49 -> 0 | G49: =F49 -> 0 | H49: =G49 -> 0 | I49: =H49 -> 0 | J49: =I49 -> 0 | K49: =J49 -> 0 | L49: =K49 -> 0 | M49: =L49 -> 0 | ... P49: =O49 -> 0 | Q49: =SUM(D49:P49) -> 0
B50: =Orcado!B44 -> Custo | F50: =E50 -> 0 | G50: =F50 -> 0 | H50: =G50 -> 0 | I50: =H50 -> 0 | J50: =I50 -> 0 | K50: =J50 -> 0 | L50: =K50 -> 0 | M50: =L50 -> 0 | ... P50: =O50 -> 0 | Q50: =SUM(D50:P50) -> 0
B51: =Orcado!B45 -> Custo | F51: =E51 -> 0 | G51: =F51 -> 0 | H51: =G51 -> 0 | I51: =H51 -> 0 | J51: =I51 -> 0 | K51: =J51 -> 0 | L51: =K51 -> 0 | M51: =L51 -> 0 | ... P51: =O51 -> 0 | Q51: =SUM(D51:P51) -> 0
B52: =Orcado!B46 -> Outros custos | F52: =E52 -> 0 | G52: =F52 -> 0 | H52: =G52 -> 0 | I52: =H52 -> 0 | J52: =I52 -> 0 | K52: =J52 -> 0 | L52: =K52 -> 0 | M52: =L52 -> 0 | ... P52: =O52 -> 0 | Q52: =SUM(D52:P52) -> 0
B57: Indicadores Financeiros
B59: NPV/VPL | D59: =NPV(Param!D4,E5:P5)+D5 -> 265498.44
B60: Payback | D60: =COUNTIF(D6:P6,"<=0") -> 0
B61: ROI | D61: =SUM(E5:P5)/-D5 -> -1.0340024

Sheet Gráfico -Status
B2: Períodos | C2: No Período (R$) | E2: Acumulado (R$) | G2: Desvio (R$) | H2: Desvio %
B3: Mês | C3: Orçado | D3: Realizado | E3: Orçado | F3: Realizado | G3: Diferença dos realizados
B4: 0 | C4: =HLOOKUP($B4,Orcado!$D$4:$P$5,2,FALSE) -> 110000 | D4: =HLOOKUP($B4,Realizado!$D$4:$P$5,2,FALSE) -> 158109 | E4: =C4 -> 110000 | F4: =D4 -> 158109 | G4: =F4-E4 -> 48109 | H4: =IF(E4=0,"",F4/E4-1) -> 0.43735455
B5: =B4+1 -> 1 | C5: =HLOOKUP($B5,Orcado!$D$4:$P$5,2,FALSE) -> 10388.23 | D5: =HLOOKUP($B5,Realizado!$D$4:$P$5,2,FALSE) -> 7987.4 | E5: =E4+C5 -> 120388.23 | F5: =F4+D5 -> 166096.4 | G5: =F5-E5 -> 45708.17 | H5: =F5/E5-1 -> 0.37967308
B6: =B5+1 -> 2 | C6: =HLOOKUP($B6,Orcado!$D$4:$P$5,2,FALSE) -> 10305.458 | D6: =HLOOKUP($B6,Realizado!$D$4:$P$5,2,FALSE) -> 8708.14 | E6: =E5+C6 -> 130693.69 | F6: =F5+D6 -> 174804.54 | G6: =F6-E6 -> 44110.852 | H6: =F6/E6-1 -> 0.33751325
B7: =B6+1 -> 3 | C7: =HLOOKUP($B7,Orcado!$D$4:$P$5,2,FALSE) -> 7986.0038 | D7: =HLOOKUP($B7,Realizado!$D$4:$P$5,2,FALSE) -> 9500.954 | E7: =E6+C7 -> 138679.69 | F7: =F6+D7 -> 184305.49 | G7: =F7-E7 -> 45625.802 | H7: =F7/E7-1 -> 0.32900132
B8: =B7+1 -> 4 | C8: =HLOOKUP($B8,Orcado!$D$4:$P$5,2,FALSE) -> 8234.6042 | D8: =HLOOKUP($B8,Realizado!$D$4:$P$5,2,FALSE) -> 10373.049 | E8: =E7+C8 -> 146914.3 | F8: =F7+D8 -> 194678.54 | G8: =F8-E8 -> 47764.247 | H8: =F8/E8-1 -> 0.3251164
B9: =B8+1 -> 5 | C9: =HLOOKUP($B9,Orcado!$D$4:$P$5,2,FALSE) -> 9058.0646 | D9: =HLOOKUP($B9,Realizado!$D$4:$P$5,2,FALSE) -> 11332.354 | E9: =E8+C9 -> 155972.36 | F9: =F8+D9 -> 206010.9 | G9: =F9-E9 -> 50038.537 | H9: =F9/E9-1 -> 0.32081669
B10: =B9+1 -> 6 | C10: =HLOOKUP($B10,Orcado!$D$4:$P$5,2,FALSE) -> 9963.8711 | D10: =HLOOKUP($B10,Realizado!$D$4:$P$5,2,FALSE) -> 12387.59 | E10: =E9+C10 -> 165936.23 | F10: =F9+D10 -> 218398.49 | G10: =F10-E10 -> 52462.256 | H10: =F10/E10-1 -> 0.31615914
B11: =B10+1 -> 7 | C11: =HLOOKUP($B11,Orcado!$D$4:$P$5,2,FALSE) -> 10960.258 | D11: =HLOOKUP($B11,Realizado!$D$4:$P$5,2,FALSE) -> 13548.349 | E11: =E10+C11 -> 176896.49 | F11: =F10+D11 -> 231946.84 | G11: =F11-E11 -> 55050.346 | H11: =F11/E11-1 -> 0.3112009
B12: =B11+1 -> 8 | C12: =HLOOKUP($B12,Orcado!$D$4:$P$5,2,FALSE) -> 12056.284 | D12: =HLOOKUP($B12,Realizado!$D$4:$P$5,2,FALSE) -> 14825.184 | E12: =E11+C12 -> 188952.77 | F12: =F11+D12 -> 246772.02 | G12: =F12-E12 -> 57819.246 | H12: =F12/E12-1 -> 0.3059984
B13: =B12+1 -> 9 | C13: =HLOOKUP($B13,Orcado!$D$4:$P$5,2,FALSE) -> 13261.912 | D13: =HLOOKUP($B13,Realizado!$D$4:$P$5,2,FALSE) -> 16229.702 | E13: =E12+C13 -> 202214.69 | F13: =F12+D13 -> 263001.72 | G13: =F13-E13 -> 60787.036 | H13: =F13/E13-1 -> 0.30060643
B14: =B13+1 -> 10 | C14: =HLOOKUP($B14,Orcado!$D$4:$P$5,2,FALSE) -> 14588.104 | D14: =HLOOKUP($B14,Realizado!$D$4:$P$5,2,FALSE) -> 17774.672 | E14: =E13+C14 -> 216802.79 | F14: =F13+D14 -> 280776.39 | G14: =F14-E14 -> 63973.604 | H14: =F14/E14-1 -> 0.2950774
B15: =B14+1 -> 11 | C15: =HLOOKUP($B15,Orcado!$D$4:$P$5,2,FALSE) -> 16046.914 | D15: =HLOOKUP($B15,Realizado!$D$4:$P$5,2,FALSE) -> 19474.139 | E15: =E14+C15 -> 232849.7 | F15: =F14+D15 -> 300250.53 | G15: =F15-E15 -> 67400.83 | H15: =F15/E15-1 -> 0.28946066
B16: =B15+1 -> 12 | C16: =HLOOKUP($B16,Orcado!$D$4:$P$5,2,FALSE) -> 17651.605 | D16: =HLOOKUP($B16,Realizado!$D$4:$P$5,2,FALSE) -> 21343.553 | E16: =E15+C16 -> 250501.31 | F16: =F15+D16 -> 321594.09 | G16: =F16-E16 -> 71092.778 | H16: =F16/E16-1 -> 0.28380202
B17: Total | C17: =SUM(C4:C16) -> 250501.31 | D17: =SUM(D4:D16) -> 321594.09
B18: Saldo Final | C18: =C17-D17 -> -71092.778

Sheet Param
B2: Variável | C2: Tipo de Benefício | D2: Custo do Capital
B3: Explicação | D3: Retorno Requerido do Investimento
B4: Domínio ou Valor | C4: Aumento de Receita | D4: 0.06
C5: Aumento de Produtividade
C6: Aumento da Capacidade Produtiva
C7: Redução do Turn-over
C8: Redução de retrabalho
C9: Redução dos custos da não qualidade
C10: Redução das reclamações dos clientes
C11: Redução dos custos
B15: Parametros a serem configurados inicialmente
B16: Projeto
B17: Nome do projeto | C17: PI ADS4 - 2025
B18: Mês de início | C18: 45891
B19: Patrocinador | C19: Cannoli

Sheet Capa
B5: Informações sobre o projeto
B6: Projeto | E6: Calogic
B7: Gerente Responsável | E7: Kaique Neres de Oliveira
B8: Data da avaliação | E8: 45944
B9: Histórico da avaliação de riscos
B10: 45908 | C10: Falhas no escopo levam atrasos e o aumento de custos. Reforçar análise de requisitos e controle de mudanças.
B11: 45915 | C11: Falhas na autenticação podem permitir acesso indevido a dados e sistemas. Recomenda-se aplicar autenticação multifator (MFA) e revisão de permissões de usuários.
B12: 45915 | C12: A ausência de plano estruturado prejudica a conformidade e resposta a incidentes. É necessário criar um plano de segurança formal e designar um responsável (DPO).
B13: 45922 | C13: APIs expostas sem controle de acesso são portas de entrada para ataques. Implementar tokens seguros (OAuth2), revisão de endpoints e testes de penetração.
B14: 45922 | C14: O chatbot pode vazar dados pessoais se não houver filtragem e anonimização. Reforçar logs, revisão de prompts e uso de máscaras de dados.
B15: 45922 | C15: Afeta diretamente a continuidade do sistema. É importante definir redundância e planos de contingência (multi-cloud ou backups offline).
B16: 45929 | C16: Exige revisão de código, aplicação de WAF e monitoramento contínuo. Implementar varreduras automáticas de vulnerabilidade.
B17: 45929 | C17: O risco envolve exposição de informações sensíveis e violações à LGPD. Exige medidas imediatas como criptografia de dados, revisão de políticas de privacidade e treinamento da equipe.
B18: 45936 | C18: Pode causar desalinhamento de expectativas e decisões incorretas. Reavaliar a matriz de stakeholders e atualizar periodicamente.
B19: 45936 | C19: Provoca instabilidade no desenvolvimento. Implantar controle de versionamento e processo formal de gestão de mudanças (change request).

Sheet Identificar
A1: Identificação dos Riscos | AF1: Probabilidade | AI1: Impacto
A4: =Capa!E6 -> Calogic
AF5: Muito Baixa - 1 | AG5: 1 | AI5: Muito Baixo - 1 | AJ5: 1
A6: ID | B6: Fase ou | D6: Declaração do Risco | G6: Resp. | H6: Estratégia de Resposta | I6: Plano de Prevenção | J6: Plano de Contingência | L6: Severidade (X,Y) | AF6: Baixa - 2 | AG6: 2 | AI6: Muito Baixo - 2 | AJ6: 2
B7: Recurso | C7: Classificação | D7: CAUSA (Começa a frase com "Como Resultado ...") | E7: RISCO (Começar a frase com "Pode ocorrer ...") | F7: CONSEQUÊNCIA (Começar a frase com "O que acarretaria ...") | K7: Riscos Colaterais | AF7: Moderada - 3 | AG7: 3 | AI7: Baixo - 3 | AJ7: 3
A8: R01 | B8: Planejamento | C8: Falhas | D8: Como resultado da falha da equipe e do gerente do projeto. | E8: Pode ocorrer de aumentar os custos e os atrasos, além de acabar com a expectativa do stakeholder. | F8: O que acarretaria capacitação para o lançamento do sistema. | H8: Mitigar | I8: Realizar reuniões, definir responsabilidades e cronogramas que sigam as datas corretamente. | J8: Replanejar o cronograma, as tarefas e contratar apoio caso necessário. | K8: Atraso no projeto e aumento nos custos | L8: =Qualificar!K8 -> 0.01 | AF8: Alta - 4 | AG8: 4 | AI8: Baixo - 4 | AJ8: 4
A9: R02 | B9: Segurança | C9: Falhas | D9: Como resultado de não implementação de segurança de autenticação. | E9: Pode ocorrer acesso indevido. | F9: O que acarretaria vazamento de dados e vulnerabilidade nos sistemas. | H9: Evitar | I9: Implementar autenticação multifator e criptografia; testar vulnerabilidades. | J9: Bloquear contas comprometidas; restaurar backups; reforçar auditoria de acessos. | L9: =Qualificar!K9 -> 0.32
A10: R03 | B10: Planejamento | C10: Ausência | D10: Como resultado da ausência de um plano de respostas a incidentes. | E10: Pode ocorrer a lentidão da resposta à ataques. | F10: O que acarretaria aumento da exposição. | H10: Mitigar | I10: Criar e documentar plano de resposta; simular ataques (testes de penetração). | J10: Ativar equipe de resposta rápida; priorizar mitigação e comunicação com stakeholders. | L10: =Qualificar!K10 -> 0.16
A11: R04 | B11: Segurança | C11: Vulnerabilidade | D11: Como resultado da falta de controle de acesso. | E11: Pode ocorrer acesso indevido e ataques. | F11: O que acarretaria vazamento de dados e vulnerabilidade nos sistemas. | H11: Evitar | I11: Configurar níveis de permissão; revisar perfis trimestralmente. | J11: Revogar acessos suspeitos; revisar logs; aplicar medidas disciplinares. | L11: =Qualificar!K11 -> 0.32
A12: R05 | B12: Segurança | C12: Vazamento | D12: Como resultado da não anonimização de dados. | E12: Pode ocorrer vazamento de dados pessoais. | F12: O que acarretaria exposição desses dados pessoais. | H12: Transferir | I12: Anonimizar dados sensíveis; revisar políticas LGPD. | J12: Acionar equipe jurídica; comunicar autoridade competente; corrigir falhas de segurança. | L12: =Qualificar!K12 -> 0.32
A13: R06 | B13: Disponibilidade | C13: Redundância | D13: Como resultado da falta de redundância e backups. | E13: Pode ocorrer comprometimento do sistema. | F13: O que acarretaria indisponibilidade do sistema. | H13: Mitigar | I13: Implementar backups automáticos e redundantes; testar restauração mensal. | J13: Restaurar sistema a partir do backup mais recente; comunicar usuários sobre indisponibilidade. | L13: =Qualificar!K13 -> 0.16
A14: R07 | B14: Sustentação | C14: Melhorias contínuas | D14: Como resultado de falta de avaliação contínua. | E14: Pode ocorrer bugs não tratados e obsoleineidade do sistema. | F14: O que acarretaria baixa satisfação do usuário. | H14: Mitigar | I14: Adotar ciclos de revisão contínua (sprints); testes automatizados. | J14: Suspender versões instáveis; corrigir falhas emergenciais. | L14: =Qualificar!K14 -> 0.02
A15: R08 | B15: Segurança | C15: Legal | D15: Como resultado da não observação das leis atuais. | E15: Pode ocorrer exposição de informações. | F15: O que acarretaria violação da LGPD e multas. | H15: Transferir | I15: Revisar legislação aplicável; aplicar políticas de privacidade. | J15: Consultar assessoria jurídica; ajustar documentação e avisos legais. | L15: =Qualificar!K15 -> 0.32
A16: R09 | B16: Planejamento | C16: Melhorias contínuas | D16: Como resultado da falta de engajamento dos parceiros. | E16: Pode ocorrer que os stakeholders se frustem. | F16: O que acarretaria desconfiança do produto. | H16: Aceitar | I16: Promover reuniões e relatórios periódicos; manter comunicação transparente. | J16: Realinhar expectativas; reforçar comunicação e demonstrar entregas.
A17: R10 | B17: Validação | C17: GMUD | D17: Como resultado da falta de gestão de mudanças. | E17: Pode ocorrer atraso no desenvolvimento. | F17: O que acarretaria atrasos e instabilidades. | H17: Mitigar | I17: Implantar processo formal de controle de mudanças (Change Management). | J17: Reverter versão anterior (rollback); ajustar documentação técnica.
A18: R11
A19: R12
A20: R13
A21: R14
A22: R15
A23: R16
A24: R17
A25: R18
A26: R19 | L26: =Qualificar!K26
A27: R20 | L27: =Qualificar!K27

Sheet Qualificar
A1: Qualificação dos Riscos | AF1: Probabilidade | AI1: Impacto
K2: Base Custo | M2: 10000 | N2: R$
K3: Base Prazo | M3: 30 | N3: dias úteis
A4: =Identificar!A4 -> Calogic
AF5: Muito Baixa - 1 | AG5: 1 | AI5: Muito Baixo - 1 | AJ5: 1
A6: ID | B6: Declaração do Risco | E6: Resp. | F6: Probabilidade do risco virar incidente (Y) | G6: Avaliação de Impacto (X) | K6: Severidade (Y,X) | M6: Custo | N6: Prazo | AF6: Baixa - 2 | AG6: 2 | AI6: Muito Baixo - 2 | AJ6: 2
B7: CAUSA (Começa a frase com "Como Resultado ...") | C7: RISCO (Começar a frase com "Pode ocorrer ...") | D7: CONSEQÜÊNCIA (Começar a frase com "O que acarretaria ...") | G7: Aumento no Custo (X1) | H7: Desvio no Cronograma (X2) | I7: (X1*X2) | J7: Resultado do Impacto (X1+X2) | L7: Riscos Colaterais | AF7: Moderada - 3 | AG7: 3 | AI7: Baixo - 3 | AJ7: 3
A8: =IF(Identificar!A8<>"",Identificar!A8,"") -> R01 | B8: =IF(Identificar!D8<>"",Identificar!D8,"") -> Como resultado da falha da equipe e do gerente do projeto. | C8: =IF(Identificar!E8<>"",Identificar!E8,"") -> Pode ocorrer de aumentar os custos e os atrasos, além de acabar com a expectativa do stakeholder. | D8: =IF(Identificar!F8<>"",Identificar!F8,"") -> O que acarretaria capacitação para o lançamento do sistema. | E8: =IF(Identificar!G8<>"",Identificar!G8,"") | F8: Baixa - 0,1 | G8: Menor que 5% - 1,10 | H8: Menor que 5% - 2,10 | I8: =IF(G8<>"",IF(H8<>"",RIGHT(G8,4)*RIGHT(H8,4),""),"") -> 2.31 | J8: =IF(I8<>"",VLOOKUP(I8,'[8]Sensibilidade ao Risco'!$E$2:$F$30,2,FALSE),"") -> Baixa - 0,10 | K8: =IF(F8<>"",IF(J8<>"",(RIGHT(J8,3))*(RIGHT(F8,3)),""),"") -> 0.01 | L8: Atraso no projeto e aumento nos custos | M8: =ROUNDUP(Quantificar!G8/Qualificar!$M$2,2) -> 1.5 | N8: =ROUNDUP(Quantificar!H8/Qualificar!$M$3,2) -> 0.5 | AF8: Alta - 4 | AG8: 4 | AI8: Baixo - 4 | AJ8: 4
A9: =IF(Identificar!A9<>"",Identificar!A9,"") -> R02 | B9: =IF(Identificar!D9<>"",Identificar!D9,"") -> Como resultado de não implementação de segurança de autenticação. | C9: =IF(Identificar!E9<>"",Identificar!E9,"") -> Pode ocorrer acesso indevido. | D9: =IF(Identificar!F9<>"",Identificar!F9,"") -> O que acarretaria vazamento de dados e vulnerabilidade nos sistemas. | E9: =IF(Identificar!G9<>"",Identificar!G9,"") | F9: Muito Alta - 0,8 | G9: Maior que 20% - 1,80 | H9: Menor que 5% - 2,10 | I9: =IF(G9<>"",IF(H9<>"",RIGHT(G9,4)*RIGHT(H9,4),""),"") -> 3.78 | J9: =IF(I9<>"",VLOOKUP(I9,'[8]Sensibilidade ao Risco'!$E$2:$F$30,2,FALSE),"") -> Alta - 0,40 | K9: =IF(F9<>"",IF(J9<>"",(RIGHT(J9,3))*(RIGHT(F9,3)),""),"") -> 0.32 | M9: =ROUNDUP(Quantificar!G9/Qualificar!$M$2,2) -> 1 | N9: =ROUNDUP(Quantificar!H9/Qualificar!$M$3,2) -> 0.34
A10: =IF(Identificar!A10<>"",Identificar!A10,"") -> R03 | B10: =IF(Identificar!D10<>"",Identificar!D10,"") -> Como resultado da ausência de um plano de respostas a incidentes. | C10: =IF(Identificar!E10<>"",Identificar!E10,"") -> Pode ocorrer a lentidão da resposta à ataques. | D10: =IF(Identificar!F10<>"",Identificar!F10,"") -> O que acarretaria aumento da exposição. | E10: =IF(Identificar!G10<>"",Identificar!G10,"") | F10: Alta - 0,4 | G10: Entre 10% e 20% - 1,40 | H10: Menor que 5% - 2,10 | I10: =IF(G10<>"",IF(H10<>"",RIGHT(G10,4)*RIGHT(H10,4),""),"") -> 2.94 | J10: =IF(I10<>"",VLOOKUP(I10,'[8]Sensibilidade ao Risco'!$E$2:$F$30,2,FALSE),"") -> Alta - 0,40 | K10: =IF(F10<>"",IF(J10<>"",(RIGHT(J10,3))*(RIGHT(F10,3)),""),"") -> 0.16 | M10: =ROUNDUP(Quantificar!G10/Qualificar!$M$2,2) -> 1.2 | N10: =ROUNDUP(Quantificar!H10/Qualificar!$M$3,2) -> 0.4
A11: =IF(Identificar!A11<>"",Identificar!A11,"") -> R04 | B11: =IF(Identificar!D11<>"",Identificar!D11,"") -> Como resultado da falta de controle de acesso. | C11: =IF(Identificar!E11<>"",Identificar!E11,"") -> Pode ocorrer acesso indevido e ataques. | D11: =IF(Identificar!F11<>"",Identificar!F11,"") -> O que acarretaria vazamento de dados e vulnerabilidade nos sistemas. | E11: =IF(Identificar!G11<>"",Identificar!G11,"") | F11: Alta - 0,4 | G11: Entre 10% e 20% - 1,40 | H11: Entre 10% e 20% - 2,40 | I11: =IF(G11<>"",IF(H11<>"",RIGHT(G11,4)*RIGHT(H11,4),""),"") -> 3.36 | J11: =IF(I11<>"",VLOOKUP(I11,'[8]Sensibilidade ao Risco'!$E$2:$F$30,2,FALSE),"") -> Muito Alta - 0,80 | K11: =IF(F11<>"",IF(J11<>"",(RIGHT(J11,3))*(RIGHT(F11,3)),""),"") -> 0.32 | M11: =ROUNDUP(Quantificar!G11/Qualificar!$M$2,2) -> 2 | N11: =ROUNDUP(Quantificar!H11/Qualificar!$M$3,2) -> 0.67
A12: =IF(Identificar!A12<>"",Identificar!A12,"") -> R05 | B12: =IF(Identificar!D12<>"",Identificar!D12,"") -> Como resultado da não anonimização de dados. | C12: =IF(Identificar!E12<>"",Identificar!E12,"") -> Pode ocorrer vazamento de dados pessoais. | D12: =IF(Identificar!F12<>"",Identificar!F12,"") -> O que acarretaria exposição desses dados pessoais. | E12: =IF(Identificar!G12<>"",Identificar!G12,"") | F12: Alta - 0,4 | G12: Maior que 20% - 1,80 | H12: Entre 5% e 10% - 2,20 | I12: =IF(G12<>"",IF(H12<>"",RIGHT(G12,4)*RIGHT(H12,4),""),"") -> 3.96 | J12: =IF(I12<>"",VLOOKUP(I12,'[8]Sensibilidade ao Risco'!$E$2:$F$30,2,FALSE),"") -> Muito Alta - 0,80 | K12: =IF(F12<>"",IF(J12<>"",(RIGHT(J12,3))*(RIGHT(F12,3)),""),"") -> 0.32 | M12: =ROUNDUP(Quantificar!G12/Qualificar!$M$2,2) -> 2.5 | N12: =ROUNDUP(Quantificar!H12/Qualificar!$M$3,2) -> 0.84
A13: =IF(Identificar!A13<>"",Identificar!A13,"") -> R06 | B13: =IF(Identificar!D13<>"",Identificar!D13,"") -> Como resultado da falta de redundância e backups. | C13: =IF(Identificar!E13<>"",Identificar!E13,"") -> Pode ocorrer comprometimento do sistema. | D13: =IF(Identificar!F13<>"",Identificar!F13,"") -> O que acarretaria indisponibilidade do sistema. | E13: =IF(Identificar!G13<>"",Identificar!G13,"") | F13: Alta - 0,4 | G13: Entre 5% e 10% - 1,20 | H13: Entre 5% e 10% - 2,20 | I13: =IF(G13<>"",IF(H13<>"",RIGHT(G13,4)*RIGHT(H13,4),""),"") -> 2.64 | J13: =IF(I13<>"",VLOOKUP(I13,'[8]Sensibilidade ao Risco'!$E$2:$F$30,2,FALSE),"") -> Alta - 0,40 | K13: =IF(F13<>"",IF(J13<>"",(RIGHT(J13,3))*(RIGHT(F13,3)),""),"") -> 0.16 | M13: =ROUNDUP(Quantificar!G13/Qualificar!$M$2,2) -> 3 | N13: =ROUNDUP(Quantificar!H13/Qualificar!$M$3,2) -> 1
A14: =IF(Identificar!A14<>"",Identificar!A14,"") -> R07 | B14: =IF(Identificar!D14<>"",Identificar!D14,"") -> Como resultado de falta de avaliação contínua. | C14: =IF(Identificar!E14<>"",Identificar!E14,"") -> Pode ocorrer bugs não tratados e obsoleineidade do sistema. | D14: =IF(Identificar!F14<>"",Identificar!F14,"") -> O que acarretaria baixa satisfação do usuário. | E14: =IF(Identificar!G14<>"",Identificar!G14,"") | F14: Moderada - 0,2 | G14: Menor que 5% - 1,10 | H14: Insignificante - 2,05 | I14: =IF(G14<>"",IF(H14<>"",RIGHT(G14,4)*RIGHT(H14,4),""),"") -> 2.255 | J14: =IF(I14<>"",VLOOKUP(I14,'[8]Sensibilidade ao Risco'!$E$2:$F$30,2,FALSE),"") -> Baixa - 0,10 | K14: =IF(F14<>"",IF(J14<>"",(RIGHT(J14,3))*(RIGHT(F14,3)),""),"") -> 0.02 | M14: =ROUNDUP(Quantificar!G14/Qualificar!$M$2,2) -> 1 | N14: =ROUNDUP(Quantificar!H14/Qualificar!$M$3,2) -> 0.34
A15: =IF(Identificar!A15<>"",Identificar!A15,"") -> R08 | B15: =IF(Identificar!D15<>"",Identificar!D15,"") -> Como resultado da não observação das leis atuais. | C15: =IF(Identificar!E15<>"",Identificar!E15,"") -> Pode ocorrer exposição de informações. | D15: =IF(Identificar!F15<>"",Identificar!F15,"") -> O que acarretaria violação da LGPD e multas. | E15: =IF(Identificar!G15<>"",Identificar!G15,"") | F15: Alta - 0,4 | G15: Maior que 20% - 1,80 | H15: Entre 5% e 10% - 2,20 | I15: =IF(G15<>"",IF(H15<>"",RIGHT(G15,4)*RIGHT(H15,4),""),"") -> 3.96 | J15: =IF(I15<>"",VLOOKUP(I15,'[8]Sensibilidade ao Risco'!$E$2:$F$30,2,FALSE),"") -> Muito Alta - 0,80 | K15: =IF(F15<>"",IF(J15<>"",(RIGHT(J15,3))*(RIGHT(F15,3)),""),"") -> 0.32 | M15: =ROUNDUP(Quantificar!G15/Qualificar!$M$2,2) -> 2 | N15: =ROUNDUP(Quantificar!H15/Qualificar!$M$3,2) -> 0.67
A16: =IF(Identificar!A16<>"",Identificar!A16,"") -> R09 | B16: =IF(Identificar!D16<>"",Identificar!D16,"") -> Como resultado da falta de engajamento dos parceiros. | C16: =IF(Identificar!E16<>"",Identificar!E16,"") -> Pode ocorrer que os stakeholders se frustem. | D16: =IF(Identificar!F16<>"",Identificar!F16,"") -> O que acarretaria desconfiança do produto. | E16: =IF(Identificar!G16<>"",Identificar!G16,"") | F16: Baixa - 0,1 | G16: Menor que 5% - 1,10 | H16: Insignificante - 2,05 | I16: =IF(G16<>"",IF(H16<>"",RIGHT(G16,4)*RIGHT(H16,4),""),"") -> 2.255 | J16: =IF(I16<>"",VLOOKUP(I16,'[8]Sensibilidade ao Risco'!$E$2:$F$30,2,FALSE),"") -> Baixa - 0,10 | K16: =IF(F16<>"",IF(J16<>"",(RIGHT(J16,3))*(RIGHT(F16,3)),""),"") -> 0.01 | M16: =ROUNDUP(Quantificar!G16/Qualificar!$M$2,2) -> 0.7 | N16: =ROUNDUP(Quantificar!H16/Qualificar!$M$3,2) -> 0.24
A17: =IF(Identificar!A17<>"",Identificar!A17,"") -> R10 | B17: =IF(Identificar!D17<>"",Identificar!D17,"") -> Como resultado da falta de gestão de mudanças. | C17: =IF(Identificar!E17<>"",Identificar!E17,"") -> Pode ocorrer atraso no desenvolvimento. | D17: =IF(Identificar!F17<>"",Identificar!F17,"") -> O que acarretaria atrasos e instabilidades. | E17: =IF(Identificar!G17<>"",Identificar!G17,"") | F17: Moderada - 0,2 | G17: Menor que 5% - 1,10 | H17: Entre 5% e 10% - 2,20 | I17: =IF(G17<>"",IF(H17<>"",RIGHT(G17,4)*RIGHT(H17,4),""),"") -> 2.42 | J17: =IF(I17<>"",VLOOKUP(I17,'[8]Sensibilidade ao Risco'!$E$2:$F$30,2,FALSE),"") -> Moderada - 0,20 | K17: =IF(F17<>"",IF(J17<>"",(RIGHT(J17,3))*(RIGHT(F17,3)),""),"") -> 0.04 | M17: =ROUNDUP(Quantificar!G17/Qualificar!$M$2,2) -> 1.5 | N17: =ROUNDUP(Quantificar!H17/Qualificar!$M$3,2) -> 0.5
A18: =IF(Identificar!A18<>"",Identificar!A18,"") -> R11 | B18: =IF(Identificar!D18<>"",Identificar!D18,"") | C18: =IF(Identificar!E18<>"",Identificar!E18,"") | D18: =IF(Identificar!F18<>"",Identificar!F18,"") | E18: =IF(Identificar!G18<>"",Identificar!G18,"") | I18: =IF(G18<>"",IF(H18<>"",RIGHT(G18,4)*RIGHT(H18,4),""),"") | J18: =IF(I18<>"",VLOOKUP(I18,'[8]Sensibilidade ao Risco'!$E$2:$F$30,2,FALSE),"") | K18: =IF(F18<>"",IF(J18<>"",(RIGHT(J18,3))*(RIGHT(F18,3)),""),"") | M18: =ROUNDUP(Quantificar!G18/Qualificar!$M$2,2) -> 0 | N18: =ROUNDUP(Quantificar!H18/Qualificar!$M$3,2) -> 0
A19: =IF(Identificar!A19<>"",Identificar!A19,"") -> R12 | B19: =IF(Identificar!D19<>"",Identificar!D19,"") | C19: =IF(Identificar!E19<>"",Identificar!E19,"") | D19: =IF(Identificar!F19<>"",Identificar!F19,"") | E19: =IF(Identificar!G19<>"",Identificar!G19,"") | I19: =IF(G19<>"",IF(H19<>"",RIGHT(G19,4)*RIGHT(H19,4),""),"") | J19: =IF(I19<>"",VLOOKUP(I19,'[8]Sensibilidade ao Risco'!$E$2:$F$30,2,FALSE),"") | K19: =IF(F19<>"",IF(J19<>"",(RIGHT(J19,3))*(RIGHT(F19,3)),""),"") | M19: =ROUNDUP(Quantificar!G19/Qualificar!$M$2,2) -> 0 | N19: =ROUNDUP(Quantificar!H19/Qualificar!$M$3,2) -> 0
A20: =IF(Identificar!A20<>"",Identificar!A20,"") -> R13 | B20: =IF(Identificar!D20<>"",Identificar!D20,"") | C20: =IF(Identificar!E20<>"",Identificar!E20,"") | D20: =IF(Identificar!F20<>"",Identificar!F20,"") | E20: =IF(Identificar!G20<>"",Identificar!G20,"") | I20: =IF(G20<>"",IF(H20<>"",RIGHT(G20,4)*RIGHT(H20,4),""),"") | J20: =IF(I20<>"",VLOOKUP(I20,'[8]Sensibilidade ao Risco'!$E$2:$F$30,2,FALSE),"") | K20: =IF(F20<>"",IF(J20<>"",(RIGHT(J20,3))*(RIGHT(F20,3)),""),"") | M20: =ROUNDUP(Quantificar!G20/Qualificar!$M$2,2) -> 0 | N20: =ROUNDUP(Quantificar!H20/Qualificar!$M$3,2) -> 0
A21: =IF(Identificar!A21<>"",Identificar!A21,"") -> R14 | B21: =IF(Identificar!D21<>"",Identificar!D21,"") | C21: =IF(Identificar!E21<>"",Identificar!E21,"") | D21: =IF(Identificar!F21<>"",Identificar!F21,"") | E21: =IF(Identificar!G21<>"",Identificar!G21,"") | I21: =IF(G21<>"",IF(H21<>"",RIGHT(G21,4)*RIGHT(H21,4),""),"") | J21: =IF(I21<>"",VLOOKUP(I21,'[8]Sensibilidade ao Risco'!$E$2:$F$30,2,FALSE),"") | K21: =IF(F21<>"",IF(J21<>"",(RIGHT(J21,3))*(RIGHT(F21,3)),""),"") | M21: =ROUNDUP(Quantificar!G21/Qualificar!$M$2,2) -> 0 | N21: =ROUNDUP(Quantificar!H21/Qualificar!$M$3,2) -> 0
A22: =IF(Identificar!A22<>"",Identificar!A22,"") -> R15 | B22: =IF(Identificar!D22<>"",Identificar!D22,"") | C22: =IF(Identificar!E22<>"",Identificar!E22,"") | D22: =IF(Identificar!F22<>"",Identificar!F22,"") | E22: =IF(Identificar!G22<>"",Identificar!G22,"") | I22: =IF(G22<>"",IF(H22<>"",RIGHT(G22,4)*RIGHT(H22,4),""),"") | J22: =IF(I22<>"",VLOOKUP(I22,'[8]Sensibilidade ao Risco'!$E$2:$F$30,2,FALSE),"") | K22: =IF(F22<>"",IF(J22<>"",(RIGHT(J22,3))*(RIGHT(F22,3)),""),"") | M22: =ROUNDUP(Quantificar!G22/Qualificar!$M$2,2) -> 0 | N22: =ROUNDUP(Quantificar!H22/Qualificar!$M$3,2) -> 0
A23: =IF(Identificar!A23<>"",Identificar!A23,"") -> R16 | B23: =IF(Identificar!D23<>"",Identificar!D23,"") | C23: =IF(Identificar!E23<>"",Identificar!E23,"") | D23: =IF(Identificar!F23<>"",Identificar!F23,"") | E23: =IF(Identificar!G23<>"",Identificar!G23,"") | I23: =IF(G23<>"",IF(H23<>"",RIGHT(G23,4)*RIGHT(H23,4),""),"") | J23: =IF(I23<>"",VLOOKUP(I23,'[8]Sensibilidade ao Risco'!$E$2:$F$30,2,FALSE),"") | K23: =IF(F23<>"",IF(J23<>"",(RIGHT(J23,3))*(RIGHT(F23,3)),""),"") | M23: =ROUNDUP(Quantificar!G23/Qualificar!$M$2,2) -> 0 | N23: =ROUNDUP(Quantificar!H23/Qualificar!$M$3,2) -> 0
A24: =IF(Identificar!A24<>"",Identificar!A24,"") -> R17 | B24: =IF(Identificar!D24<>"",Identificar!D24,"") | C24: =IF(Identificar!E24<>"",Identificar!E24,"") | D24: =IF(Identificar!F24<>"",Identificar!F24,"") | E24: =IF(Identificar!G24<>"",Identificar!G24,"") | I24: =IF(G24<>"",IF(H24<>"",RIGHT(G24,4)*RIGHT(H24,4),""),"") | J24: =IF(I24<>"",VLOOKUP(I24,'[8]Sensibilidade ao Risco'!$E$2:$F$30,2,FALSE),"") | K24: =IF(F24<>"",IF(J24<>"",(RIGHT(J24,3))*(RIGHT(F24,3)),""),"") | M24: =ROUNDUP(Quantificar!G24/Qualificar!$M$2,2) -> 0 | N24: =ROUNDUP(Quantificar!H24/Qualificar!$M$3,2) -> 0
A25: =IF(Identificar!A25<>"",Identificar!A25,"") -> R18 | B25: =IF(Identificar!D25<>"",Identificar!D25,"") | C25: =IF(Identificar!E25<>"",Identificar!E25,"") | D25: =IF(Identificar!F25<>"",Identificar!F25,"") | E25: =IF(Identificar!G25<>"",Identificar!G25,"") | I25: =IF(G25<>"",IF(H25<>"",RIGHT(G25,4)*RIGHT(H25,4),""),"") | J25: =IF(I25<>"",VLOOKUP(I25,'[8]Sensibilidade ao Risco'!$E$2:$F$30,2,FALSE),"") | K25: =IF(F25<>"",IF(J25<>"",(RIGHT(J25,3))*(RIGHT(F25,3)),""),"") | M25: =ROUNDUP(Quantificar!G25/Qualificar!$M$2,2) -> 0 | N25: =ROUNDUP(Quantificar!H25/Qualificar!$M$3,2) -> 0
A26: =IF(Identificar!A26<>"",Identificar!A26,"") -> R19 | B26: =IF(Identificar!D26<>"",Identificar!D26,"") | C26: =IF(Identificar!E26<>"",Identificar!E26,"") | D26: =IF(Identificar!F26<>"",Identificar!F26,"") | E26: =IF(Identificar!G26<>"",Identificar!G26,"") | I26: =IF(G26<>"",IF(H26<>"",RIGHT(G26,4)*RIGHT(H26,4),""),"") | J26: =IF(I26<>"",VLOOKUP(I26,'[8]Sensibilidade ao Risco'!$E$2:$F$30,2,FALSE),"") | K26: =IF(F26<>"",IF(J26<>"",(RIGHT(J26,3))*(RIGHT(F26,3)),""),"") | M26: =ROUNDUP(Quantificar!G26/Qualificar!$M$2,2) -> 0 | N26: =ROUNDUP(Quantificar!H26/Qualificar!$M$3,2) -> 0
A27: =IF(Identificar!A27<>"",Identificar!A27,"") -> R20 | B27: =IF(Identificar!D27<>"",Identificar!D27,"") | C27: =IF(Identificar!E27<>"",Identificar!E27,"") | D27: =IF(Identificar!F27<>"",Identificar!F27,"") | E27: =IF(Identificar!G27<>"",Identificar!G27,"") | I27: =IF(G27<>"",IF(H27<>"",RIGHT(G27,4)*RIGHT(H27,4),""),"") | J27: =IF(I27<>"",VLOOKUP(I27,'[8]Sensibilidade ao Risco'!$E$2:$F$30,2,FALSE),"") | K27: =IF(F27<>"",IF(J27<>"",(RIGHT(J27,3))*(RIGHT(F27,3)),""),"") | M27: =ROUNDUP(Quantificar!G27/Qualificar!$M$2,2) -> 0 | N27: =ROUNDUP(Quantificar!H27/Qualificar!$M$3,2) -> 0
F48: Insignificante - 1,05 | G48: Insignificante - 2,05 | H48: Muito baixa - 0,05
F49: Menor que 5% - 1,10 | G49: Menor que 5% - 2,10 | H49: Baixa - 0,1
F50: Entre 5% e 10% - 1,20 | G50: Entre 5% e 10% - 2,20 | H50: Moderada - 0,2
F51: Entre 10% e 20% - 1,40 | G51: Entre 10% e 20% - 2,40 | H51: Alta - 0,4
F52: Maior que 20% - 1,80 | G52: Maior que 20% - 2,80 | H52: Muito Alta - 0,8

Sheet Quantificar
A1: Quantificação dos Riscos | AB1: Probabilidade | AE1: Impacto
A4: =Identificar!A4 -> Calogic
AB5: Muito Baixa - 1 | AC5: 1 | AE5: Muito Baixo - 1 | AF5: 1
A6: ID | B6: Declaração do Risco | E6: Resp. | G6: Impacto no Custo (Considerar qtde. de horas como unidade de medida, inclusive, a maior ou menor) | H6: Impacto no Cronograma (Colocar qtde. de dias de redução ou atraso no cronograma) | I6: Observação | J6: Plano de Prevenção | K6: Plano de Contingência | AB6: Baixa - 2 | AC6: 2 | AE6: Muito Baixo - 2 | AF6: 2
B7: CAUSA (Começa a frase com "Como Resultado ...") | C7: RISCO (Começar a frase com "Pode ocorrer ...") | D7: CONSEQÜÊNCIA (Começar a frase com "O que acarretaria ...") | F7: Riscos Colaterais | AB7: Moderada - 3 | AC7: 3 | AE7: Baixo - 3 | AF7: 3
A8: =IF(Identificar!A8<>"",Identificar!A8,"") -> R01 | B8: =IF(Identificar!D8<>"",Identificar!D8,"") -> Como resultado da falha da equipe e do gerente do projeto. | C8: =IF(Identificar!E8<>"",Identificar!E8,"") -> Pode ocorrer de aumentar os custos e os atrasos, além de acabar com a expectativa do stakeholder. | D8: =IF(Identificar!F8<>"",Identificar!F8,"") -> O que acarretaria capacitação para o lançamento do sistema. | E8: Kaique Neres | F8: Retrabalho e desmotivação da equipe. | G8: 15000 | H8: 15 | I8: Replanejamento, treinamento e realinhamento com o stakeholder. | J8: =Identificar!I8 -> Realizar reuniões, definir responsabilidades e cronogramas que sigam as datas corretamente. | K8: =Identificar!J8 -> Replanejar o cronograma, as tarefas e contratar apoio caso necessário. | AB8: Alta - 4 | AC8: 4 | AE8: Baixo - 4 | AF8: 4
A9: =IF(Identificar!A9<>"",Identificar!A9,"") -> R02 | B9: =IF(Identificar!D9<>"",Identificar!D9,"") -> Como resultado de não implementação de segurança de autenticação. | C9: =IF(Identificar!E9<>"",Identificar!E9,"") -> Pode ocorrer acesso indevido. | D9: =IF(Identificar!F9<>"",Identificar!F9,"") -> O que acarretaria vazamento de dados e vulnerabilidade nos sistemas. | E9: Isabela Nunes | F9: Exposição de dados e danos à reputação. | G9: 10000 | H9: 10 | I9: Correção emergencial e exige validação de especialistas. | J9: =Identificar!I9 -> Implementar autenticação multifator e criptografia; testar vulnerabilidades. | K9: =Identificar!J9 -> Bloquear contas comprometidas; restaurar backups; reforçar auditoria de acessos.
A10: =IF(Identificar!A10<>"",Identificar!A10,"") -> R03 | B10: =IF(Identificar!D10<>"",Identificar!D10,"") -> Como resultado da ausência de um plano de respostas a incidentes. | C10: =IF(Identificar!E10<>"",Identificar!E10,"") -> Pode ocorrer a lentidão da resposta à ataques. | D10: =IF(Identificar!F10<>"",Identificar!F10,"") -> O que acarretaria aumento da exposição. | E10: Isabela Nunes | F10: Aumento do tempo e custo de recuperação em crises. | G10: 12000 | H10: 12 | I10: Tempo perdido e correções não planejadas. | J10: =Identificar!I10 -> Criar e documentar plano de resposta; simular ataques (testes de penetração). | K10: =Identificar!J10 -> Ativar equipe de resposta rápida; priorizar mitigação e comunicação com stakeholders.
A11: =IF(Identificar!A11<>"",Identificar!A11,"") -> R04 | B11: =IF(Identificar!D11<>"",Identificar!D11,"") -> Como resultado da falta de controle de acesso. | C11: =IF(Identificar!E11<>"",Identificar!E11,"") -> Pode ocorrer acesso indevido e ataques. | D11: =IF(Identificar!F11<>"",Identificar!F11,"") -> O que acarretaria vazamento de dados e vulnerabilidade nos sistemas. | E11: Luiz Felipe | F11: Vazamento interno e falhas de compliance. | G11: 20000 | H11: 20 | I11: Revisão de permissões, logs e aumento na segurança. | J11: =Identificar!I11 -> Configurar níveis de permissão; revisar perfis trimestralmente. | K11: =Identificar!J11 -> Revogar acessos suspeitos; revisar logs; aplicar medidas disciplinares.
A12: =IF(Identificar!A12<>"",Identificar!A12,"") -> R05 | B12: =IF(Identificar!D12<>"",Identificar!D12,"") -> Como resultado da não anonimização de dados. | C12: =IF(Identificar!E12<>"",Identificar!E12,"") -> Pode ocorrer vazamento de dados pessoais. | D12: =IF(Identificar!F12<>"",Identificar!F12,"") -> O que acarretaria exposição desses dados pessoais. | E12: Gabriel Pires | F12: Sanções legais e perda de confiança dos usuários. | G12: 25000 | H12: 25 | I12: Pode gerar multas por conta da LGPD e retrabalho jurídico. | J12: =Identificar!I12 -> Anonimizar dados sensíveis; revisar políticas LGPD. | K12: =Identificar!J12 -> Acionar equipe jurídica; comunicar autoridade competente; corrigir falhas de segurança.
A13: =IF(Identificar!A13<>"",Identificar!A13,"") -> R06 | B13: =IF(Identificar!D13<>"",Identificar!D13,"") -> Como resultado da falta de redundância e backups. | C13: =IF(Identificar!E13<>"",Identificar!E13,"") -> Pode ocorrer comprometimento do sistema. | D13: =IF(Identificar!F13<>"",Identificar!F13,"") -> O que acarretaria indisponibilidade do sistema. | E13: Gabriel Pires | F13: Perda de dados e paralisação de operações. | G13: 30000 | H13: 30 | I13: Impacto grave, perda de dados sensíveis, pode exigir reconstrução do ambiente. | J13: =Identificar!I13 -> Implementar backups automáticos e redundantes; testar restauração mensal. | K13: =Identificar!J13 -> Restaurar sistema a partir do backup mais recente; comunicar usuários sobre indisponibilidade.
A14: =IF(Identificar!A14<>"",Identificar!A14,"") -> R07 | B14: =IF(Identificar!D14<>"",Identificar!D14,"") -> Como resultado de falta de avaliação contínua. | C14: =IF(Identificar!E14<>"",Identificar!E14,"") -> Pode ocorrer bugs não tratados e obsoleineidade do sistema. | D14: =IF(Identificar!F14<>"",Identificar!F14,"") -> O que acarretaria baixa satisfação do usuário. | E14: Luiz Felipe | F14: Obsolescência do sistema e aumento de custos. | G14: 10000 | H14: 10 | I14: Revisões, correções de bugs e tomar cuidado com a confiança do cliente. | J14: =Identificar!I14 -> Adotar ciclos de revisão contínua (sprints); testes automatizados. | K14: =Identificar!J14 -> Suspender versões instáveis; corrigir falhas emergenciais.
A15: =IF(Identificar!A15<>"",Identificar!A15,"") -> R08 | B15: =IF(Identificar!D15<>"",Identificar!D15,"") -> Como resultado da não observação das leis atuais. | C15: =IF(Identificar!E15<>"",Identificar!E15,"") -> Pode ocorrer exposição de informações. | D15: =IF(Identificar!F15<>"",Identificar!F15,"") -> O que acarretaria violação da LGPD e multas. | E15: Kaique Neres | F15: Multas, bloqueios regulatórios e danos à imagem. | G15: 20000 | H15: 20 | I15: Multas e adequações jurídicas. | J15: =Identificar!I15 -> Revisar legislação aplicável; aplicar políticas de privacidade. | K15: =Identificar!J15 -> Consultar assessoria jurídica; ajustar documentação e avisos legais.
A16: =IF(Identificar!A16<>"",Identificar!A16,"") -> R09 | B16: =IF(Identificar!D16<>"",Identificar!D16,"") -> Como resultado da falta de engajamento dos parceiros. | C16: =IF(Identificar!E16<>"",Identificar!E16,"") -> Pode ocorrer que os stakeholders se frustem. | D16: =IF(Identificar!F16<>"",Identificar!F16,"") -> O que acarretaria desconfiança do produto. | E16: Kaique Neres | F16: Atrasos, desalinhamento e perda de qualidade. | G16: 7000 | H16: 7 | I16: Comunicação e alinhamentos precisam ser reforçados. | J16: =Identificar!I16 -> Promover reuniões e relatórios periódicos; manter comunicação transparente. | K16: =Identificar!J16 -> Realinhar expectativas; reforçar comunicação e demonstrar entregas.
A17: =IF(Identificar!A17<>"",Identificar!A17,"") -> R10 | B17: =IF(Identificar!D17<>"",Identificar!D17,"") -> Como resultado da falta de gestão de mudanças. | C17: =IF(Identificar!E17<>"",Identificar!E17,"") -> Pode ocorrer atraso no desenvolvimento. | D17: =IF(Identificar!F17<>"",Identificar!F17,"") -> O que acarretaria atrasos e instabilidades. | E17: Anderson Yavi | F17: Resistência dos usuários e instabilidade nos sistemas. | G17: 15000 | H17: 15 | I17: Mudanças sem controle geram instabilidades no sistema. | J17: =Identificar!I17 -> Implantar processo formal de controle de mudanças (Change Management). | K17: =Identificar!J17 -> Reverter versão anterior (rollback); ajustar documentação técnica.
A18: =IF(Identificar!A18<>"",Identificar!A18,"") -> R11 | B18: =IF(Identificar!D18<>"",Identificar!D18,"") | C18: =IF(Identificar!E18<>"",Identificar!E18,"") | D18: =IF(Identificar!F18<>"",Identificar!F18,"") | E18: =IF(Identificar!G18<>"",Identificar!G18,"")
A19: =IF(Identificar!A19<>"",Identificar!A19,"") -> R12 | B19: =IF(Identificar!D19<>"",Identificar!D19,"") | C19: =IF(Identificar!E19<>"",Identificar!E19,"") | D19: =IF(Identificar!F19<>"",Identificar!F19,"") | E19: =IF(Identificar!G19<>"",Identificar!G19,"")
A20: =IF(Identificar!A20<>"",Identificar!A20,"") -> R13 | B20: =IF(Identificar!D20<>"",Identificar!D20,"") | C20: =IF(Identificar!E20<>"",Identificar!E20,"") | D20: =IF(Identificar!F20<>"",Identificar!F20,"") | E20: =IF(Identificar!G20<>"",Identificar!G20,"")
A21: =IF(Identificar!A21<>"",Identificar!A21,"") -> R14 | B21: =IF(Identificar!D21<>"",Identificar!D21,"") | C21: =IF(Identificar!E21<>"",Identificar!E21,"") | D21: =IF(Identificar!F21<>"",Identificar!F21,"") | E21: =IF(Identificar!G21<>"",Identificar!G21,"")
A22: =IF(Identificar!A22<>"",Identificar!A22,"") -> R15 | B22: =IF(Identificar!D22<>"",Identificar!D22,"") | C22: =IF(Identificar!E22<>"",Identificar!E22,"") | D22: =IF(Identificar!F22<>"",Identificar!F22,"") | E22: =IF(Identificar!G22<>"",Identificar!G22,"")
A23: =IF(Identificar!A23<>"",Identificar!A23,"") -> R16 | B23: =IF(Identificar!D23<>"",Identificar!D23,"") | C23: =IF(Identificar!E23<>"",Identificar!E23,"") | D23: =IF(Identificar!F23<>"",Identificar!F23,"") | E23: =IF(Identificar!G23<>"",Identificar!G23,"")
A24: =IF(Identificar!A24<>"",Identificar!A24,"") -> R17 | B24: =IF(Identificar!D24<>"",Identificar!D24,"") | C24: =IF(Identificar!E24<>"",Identificar!E24,"") | D24: =IF(Identificar!F24<>"",Identificar!F24,"") | E24: =IF(Identificar!G24<>"",Identificar!G24,"")
A25: =IF(Identificar!A25<>"",Identificar!A25,"") -> R18 | B25: =IF(Identificar!D25<>"",Identificar!D25,"") | C25: =IF(Identificar!E25<>"",Identificar!E25,"") | D25: =IF(Identificar!F25<>"",Identificar!F25,"") | E25: =IF(Identificar!G25<>"",Identificar!G25,"")
A26: =IF(Identificar!A26<>"",Identificar!A26,"") -> R19 | B26: =IF(Identificar!D26<>"",Identificar!D26,"") | C26: =IF(Identificar!E26<>"",Identificar!E26,"") | D26: =IF(Identificar!F26<>"",Identificar!F26,"") | E26: =IF(Identificar!G26<>"",Identificar!G26,"")
A27: =IF(Identificar!A27<>"",Identificar!A27,"") -> R20 | B27: =IF(Identificar!D27<>"",Identificar!D27,"") | C27: =IF(Identificar!E27<>"",Identificar!E27,"") | D27: =IF(Identificar!F27<>"",Identificar!F27,"") | E27: =IF(Identificar!G27<>"",Identificar!G27,"")
A28: =IF(Identificar!A28<>"",Identificar!A28,"") | B28: =IF(Identificar!D28<>"",Identificar!D28,"") | C28: =IF(Identificar!E28<>"",Identificar!E28,"") | D28: =IF(Identificar!F28<>"",Identificar!F28,"") | E28: =IF(Identificar!G28<>"",Identificar!G28,"")
A29: =IF(Identificar!A29<>"",Identificar!A29,"") | B29: =IF(Identificar!D29<>"",Identificar!D29,"") | C29: =IF(Identificar!E29<>"",Identificar!E29,"") | D29: =IF(Identificar!F29<>"",Identificar!F29,"") | E29: =IF(Identificar!G29<>"",Identificar!G29,"")

Sheet Sensibilidade ao Risco
A1: Custo | B1: Peso1 | C1: Cronograma | D1: Peso2 | E1: Peso1 X Peso2 | F1: Impacto
A2: Aumento de custo Insignificante | B2: 1.05 | C2: Desvio no cronograma insignificante | D2: 2.05 | E2: =B2*D2 -> 2.1525 | F2: Muito baixa - 0,05
A3: Aumento de custo Insignificante | B3: 1.05 | C3: Desvio menor que 5% no cronograma | D3: 2.1 | E3: =B3*D3 -> 2.205 | F3: Baixa - 0,10
A4: Aumento de custo Insignificante | B4: 1.05 | C4: Desvio total entre 5% e 10% no cronograma | D4: 2.2 | E4: =B4*D4 -> 2.31 | F4: Baixa - 0,10
A5: Aumento de custo Insignificante | B5: 1.05 | C5: Desvio total entre 10% e 20% no cronograma | D5: 2.4 | E5: =B5*D5 -> 2.52 | F5: Moderada - 0,20
A6: Aumento de custo Insignificante | B6: 1.05 | C6: Desvio total maior que 20% no cronograma | D6: 2.8 | E6: =B6*D6 -> 2.94 | F6: Alta - 0,40
A8: Menos de 5% de aumento no custo | B8: 1.1 | C8: Desvio no cronograma insignificante | D8: 2.05 | E8: =B8*D8 -> 2.255 | F8: Baixa - 0,10
A9: Menos de 5% de aumento no custo | B9: 1.1 | C9: Desvio menor que 5% no cronograma | D9: 2.1 | E9: =B9*D9 -> 2.31 | F9: Baixa - 0,10
A10: Menos de 5% de aumento no custo | B10: 1.1 | C10: Desvio total entre 5% e 10% no cronograma | D10: 2.2 | E10: =B10*D10 -> 2.42 | F10: Moderada - 0,20
A11: Menos de 5% de aumento no custo | B11: 1.1 | C11: Desvio total entre 10% e 20% no cronograma | D11: 2.4 | E11: =B11*D11 -> 2.64 | F11: Alta - 0,40
A12: Menos de 5% de aumento no custo | B12: 1.1 | C12: Desvio total maior que 20% no cronograma | D12: 2.8 | E12: =B12*D12 -> 3.08 | F12: Alta - 0,40
A14: entre 5% e 10% de aumento do custo | B14: 1.2 | C14: Desvio no cronograma insignificante | D14: 2.05 | E14: =B14*D14 -> 2.46 | F14: Moderada - 0,20
A15: entre 5% e 10% de aumento do custo | B15: 1.2 | C15: Desvio menor que 5% no cronograma | D15: 2.1 | E15: =B15*D15 -> 2.52 | F15: Moderada - 0,20
... A30: Mais de 20% de aumento nos custos | B30: 1.8 | C30: Desvio total maior que 20% no cronograma | D30: 2.8 | E30: =B30*D30 -> 5.04 | F30: Muito Alta - 0,80
A31: Muito baixa - 0,05
A32: Baixa - 0,10
A33: Moderada - 0,20
A34: Alta - 0,40
A35: Muito Alta - 0,80

Sheet Plano de Comunicação
A1: 1. Identificação das principais partes interessadas no projeto (stakeholders do projeto)
A3: Quadro 01. Matriz Interesse versus Poder para o projeto
A5: Identificação Stakeholder | B5: Nível de Interesse no projeto | C5: Nível de poder no projeto | D5: Explicar a ação a ser tomada: | G5: Plano de Comunicação
A6: Cliente (Usuários Finais) | B6: Saúde pessoal, bem-estar, facilidade de uso do aplicativo. | C6: Influenciam o sucesso do aplicativo por meio do uso e feedback. | D6: Usar o aplicativo, fornecer feedback, compartilhar experiências. | G6: Data: 27/10/2025 Projeto: Cannoli | O6: Página: 01/01
A7: Product Owner | B7: Sucesso do produto, inovação na área de saúde e bem-estar. | C7: Determina a direção e as prioridades do desenvolvimento. | D7: Definir a visão do produto, priorizar recursos, tomar decisões estratégicas.
A8: Desenvolvedores | B8: Desenvolvimento de software, aprendizado contínuo. | C8: Impactam diretamente na qualidade técnica do aplicativo. | D8: Escrever código, realizar testes, resolver problemas técnicos. | G8: Ref | H8: Atividade | I8: Assunto/Conteúdo | J8: Tipo | K8: Emissor –responsavel | L8: Local | M8: Receptor | N8: Data ou Freqüência | P8: Feedback | S8: Data Feedback | X8: Obs
A9: Time Comercial | B9: Crescimento do negócio, sucesso no mercado. | C9: Impactam nas estratégias de vendas e marketing. | D9: Negociar parcerias, fechar vendas, atingir metas de receita. | G9: STK-001 | H9: Kick-off Meeting | I9: Apresentação do projeto, objetivos, escopo, stakeholders e visão do produto (dashboards personalizados) | J9: Reunião | K9: Gerente de Projeto | L9: SalaSala de Conferências / Online | M9: Todos os Stakeholders | N9: Uma vez no início do projeto | P9: Coleta de impressões e expectativas dos participantes | S9: Após 1 semana | X9: Discutir primeiros riscos e critérios de sucesso
A10: Marketing | B10: Sucesso das campanhas, crescimento da base de usuários. | C10: Moldam a percepção do aplicativo e da marca no mercado. | D10: Planejar campanhas, criar conteúdo, monitorar métricas de marketing. | G10: STK-002 | H10: Reunião de Planejamento | I10: Definição de metas, cronograma e responsabilidades por fase (planejamento, design, desenvolvimento, testes) | J10: Reunião | K10: Scrum Master | L10: Sala de Reuniões | M10: Equipe de Projeto | N10: A cada 2 semanas | P10: Alinhamento de entregas e prioridades | S10: Após cada reunião | X10: Ajustar backlog e prazos conforme andamento.
A11: UX (User Experience) | B11: Satisfação do usuário, inovação de design. | C11: Influenciam diretamente na usabilidade e na retenção de usuários. | D11: Design de interface, teste de usabilidade, feedback de design. | G11: STK-003 | H11: Reuniões Diárias (Daily Scrum) | I11: Acompanhamento de tarefas, status e impedimentos | J11: Reunião | K11: Responsável: Scrum Master | L11: Meeting / Online | M11: Equipe de Desenvolvimento | N11: Diariamente | P11: Feedback sobre progresso e bloqueios | S11: Durante reunião | X11: Duração máxima de 15 minutos
A12: Equipe de Suporte ao Cliente | B12: Satisfação do cliente, melhoria contínua do suporte. | C12: Podem influenciar a satisfação do cliente. | D12: Responder a perguntas, resolver problemas, coletar feedback do cliente. | G12: STK-004 | H12: Reunião de Acompanhamento Comercial | I12: Avaliar impacto do produto em potenciais clientes e estratégias de venda | J12: Reunião | K12: Responsável: Gerente Comercial | L12: Online / Presencial | M12: Equipe Comercial | N12: Quinzenal | P12: Feedback sobre oportunidades e leads | S12: Após cada reunião | X12: Alinhar campanhas com progresso técnico.
A13: Gerência Executiva/Alta Administração | B13: Sucesso da empresa, crescimento financeiro. | C13: Definem a estratégia e os recursos disponíveis. | D13: Estabelecer metas estratégicas, alocar recursos, tomar decisões de alto nível. | G13: STK-005 | H13: Sessão de Design e UX | I13: Discussão sobre protótipos, acessibilidade, testes de usabilidade e jornada do usuário | J13: Reunião | K13: Líder de UX | L13: Online / Presencial | M13: Equipe de Design e Desenvolvimento | N13: Semanal | P13: Feedback sobre design, cores e navegação | S13: Após cada reunião | X13: Garantir aderência às personas e critérios de UX
G14: STK-006 | H14: Revisão de Sprint | I14: Demonstração de funcionalidades desenvolvidas (dashboards, filtros, gráficos) | J14: Reunião | K14: Scrum Master | L14: Meeting | M14: Product Owner e Stakeholders | N14: A cada sprint | P14: Feedback sobre entregas e melhorias | S14: Imediatamente após reunião | X14: Registrar ajustes no backlog
G15: STK-007 | H15: Reunião Técnica | I15: Análise de integração de dados, APIs, BI e segurança (LGPD e privacidade) | J15: Reunião | K15: Líder Técnico | L15: Sala de Projeto | M15: Desenvolvedores e Equipe de Dados | N15: Quinzenal | P15: Confirmação de performance e segurança | S15: Após cada reunião | X15: Verificar logs e conformidade com LGPD
G16: STK-008 | H16: Sessão de Testes e QA | I16: Validação de cenários de teste, correção de bugs e usabilidade | J16: Reunião | K16: QA Leader | L16: Ambiente de Homologação | M16: Equipe de Testes e Dev | N16: A cada ciclo de testes | P16: Relatório de bugs e melhorias aplicadas | S16: Após homologação | X16: Garantir estabilidade antes da liberação
G17: STK-009 | H17: Demonstração do Dashboard ao Cliente | I17: Apresentação do dashboard funcional com KPIs e gráficos interativos | J17: Reunião de Demonstração | K17: Gerente de Projeto | L17: Online / Cliente | M17: Cliente e Stakeholders | N17: Pré-lançamento | P17: Feedback do cliente sobre usabilidade e métricas | S17: Após 3 dias | X17: Ajustes finais antes da produção
G18: STK-010 | H18: Reunião de Lançamento | I18: Ativação em produção e comunicação oficial | J18: Reunião | K18: Gerente de Projeto | L18: Sala de Diretoria | M18: Stakeholders Internos | N18: No dia do lançamento | P18: Confirmação de estabilidade e acessos | S18: 1 dia após lançamento | X18: Definir plano de suporte inicial
G19: STK-011 | H19: Suporte Pós-Lançamento | I19: Monitoramento e suporte nas primeiras horas/dias de uso | J19: Comunicação Interna | K19: Equipe de Suporte | L19: Canal de Suporte / Teams | M19: Stakeholders Internos | N19: Diariamente (1ª semana) | P19: Relato de incidentes e sugestões | S19: Contínuo | X19: Registro em planilha de atendimento
G20: STK-012 | H20: Reunião de Alinhamento Pós-Lançamento | I20: Avaliação das métricas iniciais de uso do dashboard. | J20: Reunião | K20: Product Owner | L20: Sala de Reuniões | M20: Equipe Técnica e Gestores | N20: Semanal (1º mês) | P20: Feedback sobre métricas e desempenho | S20: Após cada reunião | X20: Definir próximas melhorias
G21: STK-013 | H21: Sessão de Avaliação e Aperfeiçoamento | I21: Discussão de feedbacks coletados e implementação de melhorias contínuas | J21: Reunião | K21: Gerente de Projeto | L21: Online | M21: Equipe de Desenvolvimento e UX | N21: Mensal | P21: Feedback consolidado de performance | S21: Após 1 semana | X21: Revisar roadmap de melhorias
G22: STK-014 | H22: Reunião de Expansão | I22: Planejamento da versão mobile e novas oportunidades de mercado | J22: Reunião Estratégica | K22: Gerente de Projeto | L22: Sala de Reuniões | M22: Alta Administração | N22: Ao final da entrega principal | P22: Feedback sobre viabilidade e cronograma | S22: Após cada ciclo de expansão | X22: Alinhar escopo e investimentos futuros
H24: Gerente do projeto: Kaique Neres | J24: Elaborado por:Equipe Marketada
G25: Alternativas para o campo Tipo de Mensagem: Relatório executivo, Relatório operacional, Cartilha, Apostila, Prontuário de registros. Arquivo, e-Mail, Correio convencional, Carta registrada, Corrier, Telefone (voice-mail), Fax, Reunião, Apresentação, Workshop, Memorando (de/para), Jornal, Vídeo (filme VHS, AVI, etc), Quadro de avisos, Painel, Lista de discução, Internet ou Intranet, entre outras.

Sheet Planejamento de RH
C4: Gestão de RH
C6: Elaborar de acordo com o exemplo abaixo um planejamento de RH para o projeto
C8: 1 - Equipe do projeto
C10: Nome | D10: Função no projeto | E10: ORIGEM - Organização / Externo | F10: DEDICAÇÃO - Integral/ parcial/horas
C11: Kaique Neres | D11: Gerente de Projeto | E11: Gerência (Interno) | F11: 8h
C12: Isabela Nunes | D12: Gerente Administrativo/PO | E12: Gerência e Comunicação | F12: 8h
C13: Anderson Yavi | D13: Desenvolvedor de Dashboards | E13: TI - Desenvolvimento | F13: 8h
C14: Gabriel Pires | D14: Engenheiro de Dados ETL | E14: TI - Desenvolvimento | F14: 8h
C15: Luiz Felipe | D15: Desenvolvedor Full-Stack | E15: TI - Desenvolvimento | F15: 8h
C18: 2 - Planejamento do RH
C20: Gerente de Projeto
C22: Nome e cargo: Kaique Neres – Gerente de Projeto
C24: Papel: Responsável pelo planejamento, controle e execução do projeto, assegurando que escopo, prazo, custo e qualidade sejam atendidos.
C26: Perfil: Formação em Gestão de Projetos ou áreas correlatas, com experiência em coordenação de equipes multidisciplinares e uso de metodologias ágeis.
C28: Responsabilidades: Planejar e monitorar o andamento do projeto, controlar cronogramas e recursos, coordenar a comunicação entre os membros da equipe e stakeholders, e garantir o cumprimento das metas estabelecidas.
C32: Gerente Administrativo/PO
C34: Nome e cargo: Isabela Nunes – Gerente Administrativo/PO (Product Owner)
C36: Papel: Responsável pelo gerenciamento do fluxo de dados e pela definição de prioridades do produto, assegurando que as entregas atendam às necessidades do projeto.
C38: Perfil: Formação em Engenharia de Dados ou áreas correlatas, com conhecimento em banco de dados e metodologias ágeis (Scrum/Kanban).
C40: Responsabilidades: Definir requisitos e funcionalidades, gerenciar backlog, validar entregas da equipe de desenvolvimento e assegurar precisão, consistência e segurança nas informações tratadas.
C44: Desenvolvedor de Dashboards
... C76: Responsabilidades: Desenvolver interfaces e funcionalidades, integrar sistemas, apoiar na gestão de cronogramas e recursos, e assegurar que os prazos e objetivos técnicos sejam cumpridos.

Sheet Organograma da Equipe

Sheet Mapa Competência - Equipe
B8: Perfil de Qualificação | G8: MAPA DE COMPETÊNCIAS
B9: 0 | C9: Nenhum conhecimento | J9: Calogic
B10: 2 | C10: Participou de treinamento | G10: Revisado em 11/2025
B11: 5 | C11: Domínio básico | G11: Site : Cannoli
B12: 8 | C12: Experiência prática | G12: Responsável: Kaique
B13: 10 | C13: Especialista | G13: Habilitação
F14: Pessoa | G14: Planejamento de Projeto | H14: Gestão de Stakeholders | I14: Gerenciamento de Backlog / Requisitos | J14: Criação de Dashboards e Relatórios | K14: Processos ETL | L14: Modelagem e Organização de Banco de Dados | M14: Desenvolvimento Front-End | N14: Desenvolvimento Back-End | O14: Integração de APIs e Serviços Externos | P14: Utilização de VSCode e Ferramentas de Desenvolvimento | Q14: Elaborar a W.B.S | R14: Gerencia Projetos | S14: Segurança e Governança de Dados | T14: Controle de Qualidade e Testes | U14: Metodologias Ágeis (Scrum/Kanban) | V14: Comunicação e Trabalho em Equipe | W14: Planejamento e Controle de RH do Projeto | X14: (…)
D15: Kaique | G15: 10 | H15: 10 | I15: 10 | J15: 7 | K15: 7 | L15: 7 | M15: 5 | N15: 5 | O15: 5 | P15: 10 | Q15: 10 | R15: 10 | S15: 8 | T15: 10 | U15: 10 | V15: 10 | W15: 10
D16: Isabela | G16: 10 | H16: 10 | I16: 10 | J16: 7 | K16: 7 | L16: 7 | M16: 7 | N16: 8 | O16: 6 | P16: 10 | Q16: 10 | R16: 9 | S16: 8 | T16: 10 | U16: 10 | V16: 10 | W16: 10
D17: Luiz Felipe | G17: 8 | H17: 7 | I17: 7 | J17: 10 | K17: 8 | L17: 10 | M17: 10 | N17: 10 | O17: 10 | P17: 10 | Q17: 7 | R17: 6 | S17: 8 | T17: 10 | U17: 10 | V17: 10 | W17: 5
D18: Anderson | G18: 7 | H18: 7 | I18: 7 | J18: 10 | K18: 8 | L18: 7 | M18: 10 | N18: 8 | O18: 10 | P18: 10 | Q18: 7 | R18: 6 | S18: 8 | T18: 10 | U18: 10 | V18: 10 | W18: 5
D19: Gabriel | G19: 8 | H19: 8 | I19: 7 | J19: 10 | K19: 10 | L19: 10 | M19: 7 | N19: 8 | O19: 10 | P19: 10 | Q19: 5 | R19: 6 | S19: 8 | T19: 10 | U19: 10 | V19: 10 | W19: 5
B21: Modelo de registro de treinamento no local de trabalho.

Sheet Mapa de Responsabilidade
B2: 6. Matriz de Responsabilidade
D4: Equipe do Projeto
B5: Ref | C5: Etapas – Atividades | D5: KN | E5: IN | F5: LF | G5: AY | H5: GG
B6: 1A | C6: DEFINIÇÃO DE OBJETIVOS DO PROJETO | D6: A | E6: C | F6: I | G6: I | H6: I
B7: 1B | C7: FORMAÇÃO DA EQUIPE DE DESIGN E DESENVOLVIMENTO | D7: A | E7: C | F7: I | G7: I | H7: I
B8: 1C | C8: IDENTIFICAÇÃO DE FUNCIONALIDADES E RECURSOS | D8: A | E8: C | F8: E | G8: C | H8: C
B9: 1D | C9: IDENTIFICAÇÃO DE STAKEHOLDERS | D9: A | E9: C | F9: I | G9: I | H9: I
B10: 2A | C10: ANÁLISE DE MERCADO | D10: A | E10: C | F10: I | G10: C | H10: I
B11: 2B | C11: LEVANTAMENTO DE REQUISITOS | D11: A | E11: C | F11: C | G11: C | H11: E
B12: 2C | C12: DOCUMENTAÇÃO DE REQUISITOS FUNCIONAIS | D12: A | E12: C | F12: C | G12: E | H12: C
B13: 2D | C13: DOCUMENTAÇÃO DE REQUISITOS NÃO FUNCIONAIS | D13: A | E13: C | F13: E | G13: I | H13: E
B14: 2E | C14: IDENTIFICAÇÃO DO CAMINHO CRÍTICO | D14: A | E14: C | F14: I | G14: I | H14: I
B15: 2F | C15: PLANEJAMENTO DE SEGURANÇA E LGPD | D15: A | E15: C | F15: I | G15: I | H15: E
B16: 2G | C16: DEFINIÇÃO DE PROTOCOLOS DE PRIVACIDADE (DADOS) | D16: A | E16: C | F16: I | G16: I | H16: E
... B19: 3C | C19: CRIAR ÍCONES E ELEMENTOS VISUAIS | D19: I | E19: C | F19: E | G19: I | H19: I
B20: 3D | C20: GARANTIR CONSISTÊNCIA VISUAL | D20: C | E20: C | F20: E | G20: I | H20: I | J20: EQUIPE DO PROJETO
B21: 3E | C21: CRIAÇÃO DE PROTÓTIPO INTERATIVO | D21: A | E21: C | F21: I | G21: E | H21: I | J21: Kaique Neres | K21: Gerente de Projeto
B22: 3F | C22: EXPERIÊNCIA DO USUÁRIO (UX) | D22: C | E22: C | F22: E | G22: I | H22: I | J22: Isabela Nunes | K22: Gerente Administrativo
B23: 3G | C23: DEFINIÇÃO DE PERSONAS | D23: C | E23: A | F23: I | G23: I | H23: I | J23: Luiz Felipe | K23: Gerente Comercial
B24: 3H | C24: GARANTIR ACESSIBILIDADE E USABILIDADE | D24: C | E24: C | F24: E | G24: E | H24: I | J24: Anderson Yavi | K24: Desenvolvedor Sênior
B25: 3I | C25: MAPEAR JORNADA DO USUÁRIO | D25: C | E25: C | F25: E | G25: I | H25: I | J25: Gabriel Gonçalves | K25: Analista de Qualidade
B26: 3J | C26: VALIDAÇÃO INICIAL COM STAKEHOLDERS | D26: A | E26: C | F26: I | G26: I | H26: I
B27: 4A | C27: DEFINIR A ESTRUTURA DO SITE | D27: A | E27: C | F27: E | G27: C | H27: I
B28: 4B | C28: PREPARAÇÃO DO AMBIENTE | D28: A | E28: C | F28: E | G28: C | H28: C
B29: 4C | C29: CONFIGURAÇÃO DE REPOSITÓRIO GITHUB | D29: C | E29: I | F29: E | G29: I | H29: I | J29: Legenda - - Gráfico RACI (Responsabilidade, Aprovação, Consultado e Informado)
B30: 4D | C30: DEFINIÇÃO DO AMBIENTE DE HOSPEDAGEM | D30: A | E30: I | F30: E | G30: I | H30: C
B31: 4E | C31: INSTALAÇÃO DO ETL E BI | D31: C | E31: I | F31: I | G31: I | H31: E | J31: R - Responsável pela Execução
B32: 4F | C32: CÓDIGO FRONT-END | D32: C | E32: I | F32: E | G32: C | H32: I | J32: A - Responsável pela Aprovação
B33: 4G | C33: ESTRUTURAÇÃO INICIAL DE INTERFACE | D33: I | E33: I | F33: C | G33: E | H33: I | J33: C - Consultado
B34: 4H | C34: IMPLEMENTAÇÃO DE KPIs PRINCIPAIS | D34: A | E34: C | F34: I | G34: E | H34: C | J34: I - Informado
B35: 4I | C35: CRIAÇÃO DE GRÁFICOS INTERATIVOS | D35: C | E35: I | F35: C | G35: E | H35: C
B36: 4J | C36: DESENVOLVIMENTO DE FILTROS DINÂMICOS | D36: C | E36: I | F36: C | G36: E | H36: C
B37: 4K | C37: EXPORTAÇÃO DE RELATÓRIOS | D37: I | E37: I | F37: I | G37: E | H37: C
B38: 4L | C38: CÓDIGO BACK-END | D38: C | E38: I | F38: E | G38: I | H38: E
B39: 4M | C39: ESTRUTURAÇÃO DO BANCO DE DADOS | D39: C | E39: I | F39: I | G39: I | H39: E
B40: 4N | C40: CRIAÇÃO DE APIs PARA INTEGRAÇÃO FRONT-END | D40: C | E40: I | F40: E | G40: C | H40: C
B41: 4O | C41: IMPLEMENTAÇÃO DE AUTENTICAÇÃO DE PERFIS DE ACESSO | D41: A | E41: I | F41: E | G41: I | H41: I
B42: 4P | C42: IMPLEMENTAÇÃO DO PROCESSO ETL | D42: A | E42: I | F42: I | G42: I | H42: E
B43: 4Q | C43: EXTRAÇÃO DE DADOS | D43: I | E43: I | F43: I | G43: I | H43: E
B44: 4R | C44: TRANSFORMAÇÃO E LIMPEZA DOS DADOS | D44: I | E44: I | F44: I | G44: I | H44: E
B45: 4S | C45: DESENVOLVER PRINCIPAIS MÓDULOS DE IA | D45: C | E45: I | F45: E | G45: C | H45: I
B46: 4T | C46: DESENVOLVIMENTO DE FAQ INTERATIVO | D46: C | E46: C | F46: E | G46: I | H46: I
... B76: 10B | C76: IMPLEMENTAÇÃO DE APP MOBILE | D76: A | E76: C | F76: E | G76: C | H76: I

Sheet Gráfico de Gantt
E3: Saúde e bem-estar na palma da sua mão
A5: Insira o nome do Líder do projeto na célula B3. Insira a data de Início do projeto na célula E3. Início do projeto: o rótulo está na célula C3. | D5: Líder do projeto: Gerente de Projeto | E5: Início do projeto: | G5: 45160
A6: A semana de exibição na célula E4 representa a semana inicial a ser exibida no cronograma do projeto na célula I4. A data de início do projeto é considerada Semana 1. Para alterar a semana de exibição, basta inserir um novo número da semana na célula E4. A data inicial para cada semana, começando com a semana de exibição na célula E4, começa na célula I4 e é calculada automaticamente. Há 8 semanas representadas nesse modo de exibição que vão da célula I4 a célula BF4. Você não deve modificar essas células. Semana de exibição: o rótulo está na célula C4. | E6: Semana de exibição: | G6: 1 | K6: =K7 -> 45159 | R6: =R7 -> 45166 | Y6: =Y7 -> 45173 | AF6: =AF7 -> 45180 | AM6: =AM7 -> 45187 | AT6: =AT7 -> 45194 | BA6: =BA7 -> 45201 | BH6: =BH7 -> 45208
A7: As células I5 a BL5 contêm o número de dias da semana representado no bloco de células acima de cada célula de data e são calculadas automaticamente. Você não deve modificar essas células. A data de hoje é contornada em vermelho (hex #AD3815) a partir da data de hoje na linha 5, passando pela coluna de data inteira até o final do cronograma do projeto. | K7: =Início_do_projeto-WEEKDAY(Início_do_projeto,1)+2+7*(Semana_de_exibição-1) -> 45159 | L7: =K7+1 -> 45160 | M7: =L7+1 -> 45161 | N7: =M7+1 -> 45162 | O7: =N7+1 -> 45163 | P7: =O7+1 -> 45164 | Q7: =P7+1 -> 45165 | R7: =Q7+1 -> 45166 | S7: =R7+1 -> 45167 | ... BN7: =BM7+1 -> 45214
A8: Esta linha inclui cabeçalhos do cronograma do projeto que estão abaixo deles. Navegue de B6 a BL6 para ouvir o conteúdo. A primeira letra de cada dia da semana da data acima daquele cabeçalho começa na célula I6 e continua até a célula BL6. Todo o gráfico de linha do tempo de projeto é gerado automaticamente com base nas datas de início e término inseridas, usando os formatos condicionais. Não modifique o conteúdo nas células dentro das colunas após a coluna I, começando na célula I7. | D8: TAREFA | E8: ATRIBUÍDO PARA | F8: PROGRESSO | G8: INÍCIO | H8: TÉRMINO | J8: DIAS | K8: =LEFT(TEXT(K7,"ddd"),1) -> s | L8: =LEFT(TEXT(L7,"ddd"),1) -> t | M8: =LEFT(TEXT(M7,"ddd"),1) -> q | N8: =LEFT(TEXT(N7,"ddd"),1) -> q | O8: =LEFT(TEXT(O7,"ddd"),1) -> s | P8: =LEFT(TEXT(P7,"ddd"),1) -> s | Q8: =LEFT(TEXT(Q7,"ddd"),1) -> d | R8: =LEFT(TEXT(R7,"ddd"),1) -> s | ... BN8: =LEFT(TEXT(BN7,"ddd"),1) -> d
A9: Não exclua esta linha. Esta linha ficará oculta para preservar uma fórmula usada para realçar o dia atual no cronograma do projeto. | J9: =IF(OR(ISBLANK(início_da_tarefa),ISBLANK(término_da_tarefa)),"",término_da_tarefa-início_da_tarefa+1) -> 4
A10: A célula B8 contém o título do exemplo da Fase 1. Insira um novo Título na célula B8. Na célula C8, insira o nome a atribuir à fase, caso ela se aplique ao seu projeto. Na célula D8, insira o Progresso para a fase inteira, caso ela se aplique ao seu projeto. Nas células E8 e F8, insira as datas de início e término para a fase inteira, caso ela se aplique ao seu projeto. O gráfico de Gantt preenche automaticamente as datas apropriadas e sombreia de acordo com o andamento inserido. Para excluir a fase e trabalhar apenas nas tarefas, basta excluir essa linha. | D10: Iniciação | J10: =IF(OR(ISBLANK(início_da_tarefa),ISBLANK(término_da_tarefa)),"",término_da_tarefa-início_da_tarefa+1) -> 3
A11: A célula B9 contém a tarefa de exemplo "Tarefa 1". Insira um novo nome da tarefa na célula B9. Insira uma pessoa para atribuir a tarefa na célula C9. Insira o andamento da tarefa na célula D9. Uma barra de progresso é exibida na célula e fica sombreada de acordo com o número na célula. Por exemplo, 50% de progresso sombreia metade da célula. Insira a data de início da tarefa na célula E9. Insira a data de término da tarefa na célula F9. Uma barra de status sombreada das datas inseridas aparece em blocos começando na célula I9 até BL9. | D11: Definir os objetivos do aplicativo e sua proposta de valor | G11: =Início_do_projeto -> 45160 | H11: =G11+3 -> 45163 | J11: =IF(OR(ISBLANK(início_da_tarefa),ISBLANK(término_da_tarefa)),"",término_da_tarefa-início_da_tarefa+1) -> 5
A12: As linhas 10 a 13 repetem o padrão da linha 9. Repita as instruções da célula A9 para todas as linhas de tarefas nesta planilha. Substitua os dados de exemplo. Um exemplo de outra fase começa na célula A14. Continue inserindo tarefas nas células A10 a A13 ou vá para a célula A14 para saber mais. | D12: Tarefa 2 | J12: =IF(OR(ISBLANK(início_da_tarefa),ISBLANK(término_da_tarefa)),"",término_da_tarefa-início_da_tarefa+1) -> 6
D13: Tarefa 3 | J13: =IF(OR(ISBLANK(início_da_tarefa),ISBLANK(término_da_tarefa)),"",término_da_tarefa-início_da_tarefa+1) -> 3
D14: Tarefa 4 | J14: =IF(OR(ISBLANK(início_da_tarefa),ISBLANK(término_da_tarefa)),"",término_da_tarefa-início_da_tarefa+1)
D15: Tarefa 5 | J15: =IF(OR(ISBLANK(início_da_tarefa),ISBLANK(término_da_tarefa)),"",término_da_tarefa-início_da_tarefa+1) -> 5
A16: A célula à direita contém o título do exemplo da Fase 2. Você pode criar uma nova fase a qualquer momento na coluna B. Este cronograma de projeto não exige fases. Para remover a fase, basta excluir a linha. Para criar um novo bloco de fases nesta linha, digite um novo Título na célula à direita. Para continuar a adicionar tarefas à fase acima, insira uma nova linha acima desta e preencha os dados da tarefa como na instrução da célula A9. Atualize os detalhes da Fase na célula à direita, com base nas instruções da célula A8. Continue navegando para baixo nas células da coluna A para saber mais. Se você ainda não adicionou as novas linhas nesta planilha, encontrará 2 exemplos adicionais de blocos de fase que foram criados nas células B20 e B26. Caso contrário, navegue pelas células da coluna A para localizar os blocos adicionais. Repita as instruções das células A8 e A9 sempre que precisar. | D16: Título Fase 2 | J16: =IF(OR(ISBLANK(início_da_tarefa),ISBLANK(término_da_tarefa)),"",término_da_tarefa-início_da_tarefa+1) -> 6
D17: Tarefa 1 | J17: =IF(OR(ISBLANK(início_da_tarefa),ISBLANK(término_da_tarefa)),"",término_da_tarefa-início_da_tarefa+1) -> 4
D18: Tarefa 2 | J18: =IF(OR(ISBLANK(início_da_tarefa),ISBLANK(término_da_tarefa)),"",término_da_tarefa-início_da_tarefa+1) -> 3
D19: Tarefa 3 | J19: =IF(OR(ISBLANK(início_da_tarefa),ISBLANK(término_da_tarefa)),"",término_da_tarefa-início_da_tarefa+1) -> 4
D20: Tarefa 4 | J20: =IF(OR(ISBLANK(início_da_tarefa),ISBLANK(término_da_tarefa)),"",término_da_tarefa-início_da_tarefa+1)
D21: Tarefa 5 | J21: =IF(OR(ISBLANK(início_da_tarefa),ISBLANK(término_da_tarefa)),"",término_da_tarefa-início_da_tarefa+1) -> 6
A22: Bloco de título de fase de exemplo | D22: Título Fase 3 | J22: =IF(OR(ISBLANK(início_da_tarefa),ISBLANK(término_da_tarefa)),"",término_da_tarefa-início_da_tarefa+1) -> 5
D23: Tarefa 1 | J23: =IF(OR(ISBLANK(início_da_tarefa),ISBLANK(término_da_tarefa)),"",término_da_tarefa-início_da_tarefa+1) -> 6
D24: Tarefa 2 | J24: =IF(OR(ISBLANK(início_da_tarefa),ISBLANK(término_da_tarefa)),"",término_da_tarefa-início_da_tarefa+1) -> 5
D25: Tarefa 3 | J25: =IF(OR(ISBLANK(início_da_tarefa),ISBLANK(término_da_tarefa)),"",término_da_tarefa-início_da_tarefa+1) -> 5
D26: Tarefa 4 | J26: =IF(OR(ISBLANK(início_da_tarefa),ISBLANK(término_da_tarefa)),"",término_da_tarefa-início_da_tarefa+1)
D27: Tarefa 5 | J27: =IF(OR(ISBLANK(início_da_tarefa),ISBLANK(término_da_tarefa)),"",término_da_tarefa-início_da_tarefa+1) -> #VALUE!
A28: Bloco de título de fase de exemplo | D28: Título Fase 4 | J28: =IF(OR(ISBLANK(início_da_tarefa),ISBLANK(término_da_tarefa)),"",término_da_tarefa-início_da_tarefa+1) -> #VALUE!
D29: Tarefa 1 | G29: data | H29: data | J29: =IF(OR(ISBLANK(início_da_tarefa),ISBLANK(término_da_tarefa)),"",término_da_tarefa-início_da_tarefa+1) -> #VALUE!
D30: Tarefa 2 | G30: data | H30: data | J30: =IF(OR(ISBLANK(início_da_tarefa),ISBLANK(término_da_tarefa)),"",término_da_tarefa-início_da_tarefa+1) -> #VALUE!
D31: Tarefa 3 | G31: data | H31: data | J31: =IF(OR(ISBLANK(início_da_tarefa),ISBLANK(término_da_tarefa)),"",término_da_tarefa-início_da_tarefa+1) -> #VALUE!
D32: Tarefa 4 | G32: data | H32: data | J32: =IF(OR(ISBLANK(início_da_tarefa),ISBLANK(término_da_tarefa)),"",término_da_tarefa-início_da_tarefa+1)
D33: Tarefa 5 | G33: data | H33: data | J33: =IF(OR(ISBLANK(início_da_tarefa),ISBLANK(término_da_tarefa)),"",término_da_tarefa-início_da_tarefa+1)
A34: Esta é uma linha vazia | J34: =IF(OR(ISBLANK(início_da_tarefa),ISBLANK(término_da_tarefa)),"",término_da_tarefa-início_da_tarefa+1)
A35: Esta linha marca o final do Cronograma do projeto. NÃO insira nada nessa linha. Insira novas linhas ACIMA desta linha para continuar a construção do cronograma de projeto. | D35: Insira novas linhas ACIMA desta | J35: =IF(OR(ISBLANK(início_da_tarefa),ISBLANK(término_da_tarefa)),"",término_da_tarefa-início_da_tarefa+1)

Sheet PV_dependência
A3: Soma de Custos
A4: Dependência | B4: Responsável | C4: Etapas – Atividades - | D4: Ref | E4: Total
A5: 1.1 | B5: GERENTE DE PROJETO | C5: Definir os objetivos do aplicativo e sua proposta de valor | D5: 1.1 | E5: 1000
C6: Formar uma equipe de desenvolvimento e design | D6: 1.3 | E6: 1000
C7: Identificar as principais funcionalidades e recursos a serem incluídos | D7: 1.2 | E7: 2000
A8: 1.3 | B8: DESIGN | C8: Realizar o design da interface do usuário (UI) | D8: 3.1 | E8: 2000
B9: GERENTE DE PROJETO | C9: Definir os requisitos detalhados do aplicativo (escopo) | D9: 2.2 | E9: 700
B10: (vazio) | C10: Planejamento | D10: 2
A11: 10.1.1 | B11: DESEMPENHO | C11: Realizar análises regulares sobre o desempenho do aplicativo | D11: 10.1.1 | E11: 4000
A12: 10.1.2 | B12: COMERCIAL | C12: Explorar parcerias com empresas relacionadas à saúde e bem-estar | D12: 10.1.2 | E12: 1000
A13: 10.1.3 | B13: COMERCIAL | C13: Avaliar a possibilidade de oferecer versões premium ou modelos de assinatura | D13: 10.1.3 | E13: 1000
A14: 2.1 | B14: GERENTE DE PROJETO | C14: Realizar uma análise de mercado para entender concorrentes e demandas | D14: 2.1 | E14: 2000
A15: 2.2 | B15: GERENTE DE PROJETO | C15: Criar um cronograma detalhado com marcos e prazos | D15: 2.3 | E15: 400
C16: Dicas de saúde e bem-estar | D16: 2.2.1 | E16: 500
C17: Integração com sistemas de monitoramento de saúde | D17: 2.2.4 | E17: 200
C18: Mapas com locais de academias e parques | D18: 2.2.3 | E18: 800
C19: Planos de exercícios físicos personalizados | D19: 2.2.2 | E19: 1000
A20: 2.3 | B20: (vazio) | C20: Design e Prototipagem | D20: 3
A21: 3.1 | B21: DESIGN | C21: Navegação simples entre as funcionalidades | D21: 3.1.1 | E21: 500
A22: 3.1.1 | B22: DESIGN | C22: Criar protótipos interativos para validar o fluxo de usuário | D22: 3.1.2 | E22: 500
A23: 3.1.2 | B23: DESIGN | C23: Experiência do usuário (UX) | D23: 3.2 | E23: 1000
A24: 3.2 | B24: DESIGN | C24: Interface limpa e intuitiva | D24: 3.2.1 | E24: 500
A25: 3.2.1 | B25: (vazio) | C25: Desenvolvimento | D25: 4
A26: 3.2.2 | B26: DESIGN | C26: Teste de UI / UX | D26: 3.2.2 | E26: 700
A27: 4.1 | B27: DESENVOLVIMENTO | C27: Desenvolver a estrutura do aplicativo | D27: 4.1 | E27: 500
A28: 4.1.2 | B28: DESENVOLVIMENTO | C28: Front-end: Interface do usuário e interações | D28: 4.1.2 | E28: 5000
A29: 4.2 | B29: DESENVOLVIMENTO | C29: Implementar as funcionalidades principais | D29: 4.2 | E29: 700
A30: 4.2.1 | B30: DESENVOLVIMENTO | C30: Módulo de dicas de saúde | D30: 4.2.1 | E30: 500
A31: 4.2.2 | B31: DESENVOLVIMENTO | C31: Gerador de planos de exercícios | D31: 4.2.2 | E31: 300
A32: 4.2.3 | B32: DESENVOLVIMENTO | C32: Integração com APIs de mapas para localização de academias e parques | D32: 4.2.3 | E32: 1000
A33: 5.1 | B33: SEGURANÇA | C33: Integrar o aplicativo com sistemas de monitoramento de saúde, como dispositivos wearable ou aplicativos de rastreamento | D33: 5.1 | E33: 3000
A34: 5.2 | B34: SEGURANÇA | C34: Garantir a segurança e privacidade dos dados do usuário | D34: 5.2 | E34: 1000
A35: 5.3 | B35: SEGURANÇA | C35: Testar a integração para assegurar que os dados são sincronizados corretamente | D35: 5.3 | E35: 1000
A36: 6.1 | B36: QUALIDADE | C36: Realizar testes de qualidade e desempenho em diversas plataformas (iOS, Android) | D36: 6.1 | E36: 30000
A37: 6.1.2 | B37: UX | C37: Testar a usabilidade do aplicativo com usuários reais | D37: 6.1.2 | E37: 700
... A47: 9.1.3 | B47: EQUIPE TÉCNICA | C47: Realizar campanhas de mídia social e anúncios online | D47: 9.1.3 | E47: 10000
A48: (vazio) | B48: (vazio) | C48: Avaliação e Aperfeiçoamento | D48: 10
C49: Iniciação | D49: 1
C50: Integração com sistemas de monitoramento de saúde | D50: 5
C51: Lançamento | D51: 7
C52: Marketing e Divulgação | D52: 9
C53: Pós-lançamento | D53: 8
C54: Testes | D54: 6
A55: Total Geral | E55: 150000

Sheet Cronograma_de_Custos (2)
B2: 5.2. CRONOGRAMA DE CUSTOS
B5: Ref | C5: Etapas – Atividades - Marcos
D6: 1 | E6: 2 | F6: 3 | G6: 4 | H6: 5 | I6: 6 | J6: 7 | K6: 8 | L6: 9 | M6: 10 | N6: 11 | O6: 12 | P6: 13 | Q6: 14 | R6: 15 | S6: 16 | T6: 17 | U6: 18 | V6: 19 | W6: 20 | X6: 21 | Y6: 22 | Z6: 23 | AA6: 24
D7: Agosto | H7: Setembro | L7: Outubro | P7: Novembro | T7: Dezembro | X7: Janeiro
B8: 1.1 | C8: Plano do Projeto | D8: 30000
B9: 1.2 | C9: Controle | H9: 5000 | L9: 5000 | P9: 5000 | T9: 5000
B10: 1.3 | C10: Fechamento | X10: 10000
B11: 2 | C11: Adequar o Espaço Físico | L11: 20000 | P11: 40000 | T11: 10000 | X11: 10000
B12: 3.1 | C12: Equipamentos de Ginástica | H12: 10000 | L12: 25000 | P12: 25000 | T12: 25000 | X12: 5000
B13: 3.2 | C13: Equipamentos de Apoio e Administração | L13: 15000 | P13: 15000 | T13: 20000 | X13: 10000
B14: 4 | C14: Contratar Mão de Obra | X14: 7000
B15: 5.1 | C15: Contratar empresa para informatização da academia | T15: 4000 | X15: 4000
B16: 5.2 | C16: Adquirir Sistemas de Segurança | T16: 2500 | X16: 2500
B17: 5.3 | C17: Fechar Convênio com Estacionamento próximo ao local | X17: 0
B18: 5.4 | C18: Contratação de Designer de Interiores | H18: =20000*35% -> 7000 | L18: =13000/4 -> 3250 | P18: =13000/4 -> 3250 | T18: =13000/4 -> 3250 | X18: =13000/4 -> 3250
